<?xml version="1.0" encoding="UTF-8" standalone="yes"?>
<Ergebniseingang>
    <WahlMetadaten>
        <File Ursprungsname="erg3_0009501.xml" Erstellungszeit="2017-08-25T11:12:38.818+02:00" ErstellungszeitMillis="1503652358818" Ursprungsserver="wahltest1l.wi.stba.de" FileVersion="1"/>
        <Wahl Wahlart="BUNDESTAGSWAHL_BUND" Wahltermin="2017-09-24+02:00" WahlId="BTW_BUND 17" GebietsartAuswertungseinheit="WAHLKREIS" GebietsartWahleinheit="WAHLKREIS" GebietsartFExport="WAHLKREIS" GebietsartBestaetigung="LAND"/>
        <Lauf Programm="WAS" Version="1.12.2" Startzeit="1970-01-05T02:29:39.402+01:00" Master="wahltest1l.wi.stba.de" Server="wahltest1l.wi.stba.de">
            <Daten Eingabe="VORLAEUFIG" Vergleich="VORPERIODE" Qualitaet="PRODUKTION" Status="ZWISCHENERGEBNIS" ZustSeqNr="0"/>
            <Stimmeingabe>
                <Eingabestand AuswertungseinheitenEingegangen="63" AuswertungseinheitenGesamt="299" LetzteAuswertungseinheit="95" Eingang="2017-08-25T11:12:31.000+02:00"/>
            </Stimmeingabe>
        </Lauf>
    </WahlMetadaten>
    <Gebietsergebnis ZeitErstEintreffen="2017-08-25T11:12:35.000+02:00" ZeitLetzteKorrektur="2017-08-25T11:12:35.000+02:00" AuswertungseinheitenErwartet="299" AuswertungseinheitenEingetroffen="63" ErgebnisVollstaendig="false" NrAenderung="0" Gebietsnummer="99" Gebietsart="BUND" AuswertungseinheitenGesamt="299">
        <GebietText>Bundesgebiet</GebietText>
        <Gruppenergebnis Gruppe="100" Gruppenart="ALLGEMEIN" Name="Wahlberechtigte">
            <Stimmergebnis Stimmart="KEINE" Anzahl="13150923" Prozent="n/a" AnzahlVergleich="13150923" ProzentVergleich="n/a" Differenz="0" ProzentDifferenz="n/a"/>
        </Gruppenergebnis>
        <Gruppenergebnis Gruppe="200" Gruppenart="ALLGEMEIN" Name="Wähler">
            <Stimmergebnis Stimmart="KEINE" Anzahl="9602584" Prozent="73.018327" AnzahlVergleich="9602584" ProzentVergleich="15.501315" Differenz="0" ProzentDifferenz="57.517012"/>
        </Gruppenergebnis>
        <Gruppenergebnis Gruppe="300" Gruppenart="ALLGEMEIN" Name="Ungültige">
            <Stimmergebnis Stimmart="DIREKT" Anzahl="363349" Prozent="3.783866" AnzahlVergleich="122336" ProzentVergleich="1.273990" Differenz="241013" ProzentDifferenz="2.509877"/>
            <Stimmergebnis Stimmart="LISTE" Anzahl="220554" Prozent="2.296819" AnzahlVergleich="104446" ProzentVergleich="1.087686" Differenz="116108" ProzentDifferenz="1.209133"/>
        </Gruppenergebnis>
        <Gruppenergebnis Gruppe="400" Gruppenart="ALLGEMEIN" Name="Gültige">
            <Stimmergebnis Stimmart="DIREKT" Anzahl="9239235" Prozent="96.216133" AnzahlVergleich="9480248" ProzentVergleich="98.726010" Differenz="-241013" ProzentDifferenz="-2.509877"/>
            <Stimmergebnis Stimmart="LISTE" Anzahl="9382030" Prozent="97.703180" AnzahlVergleich="9498138" ProzentVergleich="98.912314" Differenz="-116108" ProzentDifferenz="-1.209133"/>
        </Gruppenergebnis>
        <Gruppenergebnis Gruppe="2" Gruppenart="PARTEI" Name="CDU">
            <Stimmergebnis Stimmart="DIREKT" Anzahl="4078620" Prozent="44.144563" AnzahlVergleich="4078620" ProzentVergleich="43.022292" Differenz="0" ProzentDifferenz="1.122272"/>
            <Stimmergebnis Stimmart="LISTE" Anzahl="3748595" Prozent="39.955052" AnzahlVergleich="3748595" ProzentVergleich="39.466630" Differenz="0" ProzentDifferenz="0.488422"/>
        </Gruppenergebnis>
        <Gruppenergebnis Gruppe="1" Gruppenart="PARTEI" Name="SPD">
            <Stimmergebnis Stimmart="DIREKT" Anzahl="3485045" Prozent="37.720060" AnzahlVergleich="3485045" ProzentVergleich="36.761116" Differenz="0" ProzentDifferenz="0.958944"/>
            <Stimmergebnis Stimmart="LISTE" Anzahl="3006320" Prozent="32.043385" AnzahlVergleich="3006320" ProzentVergleich="31.651677" Differenz="0" ProzentDifferenz="0.391708"/>
        </Gruppenergebnis>
        <Gruppenergebnis Gruppe="34" Gruppenart="PARTEI" Name="DIE LINKE">
            <Stimmergebnis Stimmart="DIREKT" Anzahl="454477" Prozent="4.918989" AnzahlVergleich="461139" ProzentVergleich="4.864208" Differenz="-6662" ProzentDifferenz="0.054782"/>
            <Stimmergebnis Stimmart="LISTE" Anzahl="554621" Prozent="5.911524" AnzahlVergleich="554621" ProzentVergleich="5.839260" Differenz="0" ProzentDifferenz="0.072264"/>
        </Gruppenergebnis>
        <Gruppenergebnis Gruppe="5" Gruppenart="PARTEI" Name="GRÜNE">
            <Stimmergebnis Stimmart="DIREKT" Anzahl="713879" Prozent="7.726602" AnzahlVergleich="713879" ProzentVergleich="7.530172" Differenz="0" ProzentDifferenz="0.196431"/>
            <Stimmergebnis Stimmart="LISTE" Anzahl="909327" Prozent="9.692220" AnzahlVergleich="909327" ProzentVergleich="9.573740" Differenz="0" ProzentDifferenz="0.118480"/>
        </Gruppenergebnis>
        <Gruppenergebnis Gruppe="3" Gruppenart="PARTEI" Name="CSU">
            <Stimmergebnis Stimmart="DIREKT" Anzahl="n/a" Prozent="0.000000" AnzahlVergleich="n/a" ProzentVergleich="0.000000" Differenz="n/a" ProzentDifferenz="0.000000"/>
            <Stimmergebnis Stimmart="LISTE" Anzahl="n/a" Prozent="0.000000" AnzahlVergleich="n/a" ProzentVergleich="0.000000" Differenz="n/a" ProzentDifferenz="0.000000"/>
        </Gruppenergebnis>
        <Gruppenergebnis Gruppe="4" Gruppenart="PARTEI" Name="FDP">
            <Stimmergebnis Stimmart="DIREKT" Anzahl="204700" Prozent="2.215551" AnzahlVergleich="204700" ProzentVergleich="2.159226" Differenz="0" ProzentDifferenz="0.056325"/>
            <Stimmergebnis Stimmart="LISTE" Anzahl="470523" Prozent="5.015151" AnzahlVergleich="470523" ProzentVergleich="4.953845" Differenz="0" ProzentDifferenz="0.061306"/>
        </Gruppenergebnis>
        <Gruppenergebnis Gruppe="35" Gruppenart="PARTEI" Name="AfD">
            <Stimmergebnis Stimmart="DIREKT" Anzahl="214040" Prozent="2.316642" AnzahlVergleich="219559" ProzentVergleich="2.315963" Differenz="-5519" ProzentDifferenz="0.000679"/>
            <Stimmergebnis Stimmart="LISTE" Anzahl="376915" Prozent="4.017414" AnzahlVergleich="376915" ProzentVergleich="3.968304" Differenz="0" ProzentDifferenz="0.049110"/>
        </Gruppenergebnis>
        <Gruppenergebnis Gruppe="8" Gruppenart="PARTEI" Name="PIRATEN">
            <Stimmergebnis Stimmart="DIREKT" Anzahl="48951" Prozent="0.529816" AnzahlVergleich="176691" ProzentVergleich="1.863780" Differenz="-127740" ProzentDifferenz="-1.333963"/>
            <Stimmergebnis Stimmart="LISTE" Anzahl="134499" Prozent="1.433581" AnzahlVergleich="191221" ProzentVergleich="2.013247" Differenz="-56722" ProzentDifferenz="-0.579666"/>
        </Gruppenergebnis>
        <Gruppenergebnis Gruppe="21" Gruppenart="PARTEI" Name="NPD">
            <Stimmergebnis Stimmart="DIREKT" Anzahl="6458" Prozent="0.069897" AnzahlVergleich="78290" ProzentVergleich="0.825822" Differenz="-71832" ProzentDifferenz="-0.755924"/>
            <Stimmergebnis Stimmart="LISTE" Anzahl="75301" Prozent="0.802608" AnzahlVergleich="75301" ProzentVergleich="0.792797" Differenz="0" ProzentDifferenz="0.009812"/>
        </Gruppenergebnis>
        <Gruppenergebnis Gruppe="45" Gruppenart="PARTEI" Name="FREIE WÄHLER">
            <Stimmergebnis Stimmart="DIREKT" Anzahl="24544" Prozent="0.265649" AnzahlVergleich="39840" ProzentVergleich="0.420242" Differenz="-15296" ProzentDifferenz="-0.154592"/>
            <Stimmergebnis Stimmart="LISTE" Anzahl="40800" Prozent="0.434873" AnzahlVergleich="40800" ProzentVergleich="0.429558" Differenz="0" ProzentDifferenz="0.005316"/>
        </Gruppenergebnis>
        <Gruppenergebnis Gruppe="9" Gruppenart="PARTEI" Name="Tierschutzpartei">
            <Stimmergebnis Stimmart="DIREKT" Anzahl="n/a" Prozent="0.000000" AnzahlVergleich="n/a" ProzentVergleich="0.000000" Differenz="n/a" ProzentDifferenz="0.000000"/>
            <Stimmergebnis Stimmart="LISTE" Anzahl="33809" Prozent="0.360359" AnzahlVergleich="50152" ProzentVergleich="0.528019" Differenz="-16343" ProzentDifferenz="-0.167660"/>
        </Gruppenergebnis>
        <Gruppenergebnis Gruppe="22" Gruppenart="PARTEI" Name="ÖDP">
            <Stimmergebnis Stimmart="DIREKT" Anzahl="637" Prozent="0.006894" AnzahlVergleich="637" ProzentVergleich="0.006719" Differenz="0" ProzentDifferenz="0.000176"/>
            <Stimmergebnis Stimmart="LISTE" Anzahl="5247" Prozent="0.055926" AnzahlVergleich="5247" ProzentVergleich="0.055242" Differenz="0" ProzentDifferenz="0.000684"/>
        </Gruppenergebnis>
        <Gruppenergebnis Gruppe="37" Gruppenart="PARTEI" Name="Die PARTEI">
            <Stimmergebnis Stimmart="DIREKT" Anzahl="5535" Prozent="0.059907" AnzahlVergleich="5535" ProzentVergleich="0.058385" Differenz="0" ProzentDifferenz="0.001523"/>
            <Stimmergebnis Stimmart="LISTE" Anzahl="18094" Prozent="0.192858" AnzahlVergleich="18094" ProzentVergleich="0.190500" Differenz="0" ProzentDifferenz="0.002358"/>
        </Gruppenergebnis>
        <Gruppenergebnis Gruppe="18" Gruppenart="PARTEI" Name="BP">
            <Stimmergebnis Stimmart="DIREKT" Anzahl="n/a" Prozent="0.000000" AnzahlVergleich="n/a" ProzentVergleich="0.000000" Differenz="n/a" ProzentDifferenz="0.000000"/>
            <Stimmergebnis Stimmart="LISTE" Anzahl="n/a" Prozent="0.000000" AnzahlVergleich="n/a" ProzentVergleich="0.000000" Differenz="n/a" ProzentDifferenz="0.000000"/>
        </Gruppenergebnis>
        <Gruppenergebnis Gruppe="40" Gruppenart="PARTEI" Name="Volksabstimmung">
            <Stimmergebnis Stimmart="DIREKT" Anzahl="1748" Prozent="0.018919" AnzahlVergleich="1748" ProzentVergleich="0.018438" Differenz="0" ProzentDifferenz="0.000481"/>
            <Stimmergebnis Stimmart="LISTE" Anzahl="4712" Prozent="0.050223" AnzahlVergleich="4712" ProzentVergleich="0.049610" Differenz="0" ProzentDifferenz="0.000614"/>
        </Gruppenergebnis>
        <Gruppenergebnis Gruppe="36" Gruppenart="PARTEI" Name="PDV">
            <Stimmergebnis Stimmart="DIREKT" Anzahl="n/a" Prozent="0.000000" AnzahlVergleich="n/a" ProzentVergleich="0.000000" Differenz="n/a" ProzentDifferenz="0.000000"/>
            <Stimmergebnis Stimmart="LISTE" Anzahl="n/a" Prozent="0.000000" AnzahlVergleich="1868" ProzentVergleich="0.019667" Differenz="n/a" ProzentDifferenz="-0.019667"/>
        </Gruppenergebnis>
        <Gruppenergebnis Gruppe="17" Gruppenart="PARTEI" Name="MLPD">
            <Stimmergebnis Stimmart="DIREKT" Anzahl="601" Prozent="0.006504" AnzahlVergleich="601" ProzentVergleich="0.006339" Differenz="0" ProzentDifferenz="0.000166"/>
            <Stimmergebnis Stimmart="LISTE" Anzahl="2828" Prozent="0.030142" AnzahlVergleich="2828" ProzentVergleich="0.029774" Differenz="0" ProzentDifferenz="0.000369"/>
        </Gruppenergebnis>
        <Gruppenergebnis Gruppe="12" Gruppenart="PARTEI" Name="BüSo">
            <Stimmergebnis Stimmart="DIREKT" Anzahl="n/a" Prozent="0.000000" AnzahlVergleich="480" ProzentVergleich="0.005063" Differenz="n/a" ProzentDifferenz="-0.005063"/>
            <Stimmergebnis Stimmart="LISTE" Anzahl="n/a" Prozent="0.000000" AnzahlVergleich="451" ProzentVergleich="0.004748" Differenz="n/a" ProzentDifferenz="-0.004748"/>
        </Gruppenergebnis>
        <Gruppenergebnis Gruppe="15" Gruppenart="PARTEI" Name="SGP">
            <Stimmergebnis Stimmart="DIREKT" Anzahl="n/a" Prozent="0.000000" AnzahlVergleich="n/a" ProzentVergleich="0.000000" Differenz="n/a" ProzentDifferenz="0.000000"/>
            <Stimmergebnis Stimmart="LISTE" Anzahl="439" Prozent="0.004679" AnzahlVergleich="439" ProzentVergleich="0.004622" Differenz="0" ProzentDifferenz="0.000057"/>
        </Gruppenergebnis>
        <Gruppenergebnis Gruppe="14" Gruppenart="PARTEI" Name="DIE RECHTE">
            <Stimmergebnis Stimmart="DIREKT" Anzahl="n/a" Prozent="0.000000" AnzahlVergleich="n/a" ProzentVergleich="0.000000" Differenz="n/a" ProzentDifferenz="0.000000"/>
            <Stimmergebnis Stimmart="LISTE" Anzahl="n/a" Prozent="0.000000" AnzahlVergleich="419" ProzentVergleich="0.004411" Differenz="n/a" ProzentDifferenz="-0.004411"/>
        </Gruppenergebnis>
        <Gruppenergebnis Gruppe="41" Gruppenart="PARTEI" Name="AD-DEMOKRATEN">
            <Stimmergebnis Stimmart="LISTE" Anzahl="n/a" Prozent="0.000000" AnzahlVergleich="n/a" ProzentVergleich="0.000000" Differenz="n/a" ProzentDifferenz="0.000000"/>
        </Gruppenergebnis>
        <Gruppenergebnis Gruppe="10" Gruppenart="PARTEI" Name="Tierschutzallianz">
            <Stimmergebnis Stimmart="DIREKT" Anzahl="n/a" Prozent="0.000000" AnzahlVergleich="n/a" ProzentVergleich="0.000000" Differenz="n/a" ProzentDifferenz="0.000000"/>
            <Stimmergebnis Stimmart="LISTE" Anzahl="n/a" Prozent="0.000000" AnzahlVergleich="n/a" ProzentVergleich="0.000000" Differenz="n/a" ProzentDifferenz="0.000000"/>
        </Gruppenergebnis>
        <Gruppenergebnis Gruppe="26" Gruppenart="PARTEI" Name="B*">
            <Stimmergebnis Stimmart="DIREKT" Anzahl="n/a" Prozent="0.000000" AnzahlVergleich="n/a" ProzentVergleich="0.000000" Differenz="n/a" ProzentDifferenz="0.000000"/>
            <Stimmergebnis Stimmart="LISTE" Anzahl="n/a" Prozent="0.000000" AnzahlVergleich="n/a" ProzentVergleich="0.000000" Differenz="n/a" ProzentDifferenz="0.000000"/>
        </Gruppenergebnis>
        <Gruppenergebnis Gruppe="29" Gruppenart="PARTEI" Name="BGE">
            <Stimmergebnis Stimmart="LISTE" Anzahl="n/a" Prozent="0.000000" AnzahlVergleich="n/a" ProzentVergleich="0.000000" Differenz="n/a" ProzentDifferenz="0.000000"/>
        </Gruppenergebnis>
        <Gruppenergebnis Gruppe="24" Gruppenart="PARTEI" Name="DiB">
            <Stimmergebnis Stimmart="LISTE" Anzahl="n/a" Prozent="0.000000" AnzahlVergleich="n/a" ProzentVergleich="0.000000" Differenz="n/a" ProzentDifferenz="0.000000"/>
        </Gruppenergebnis>
        <Gruppenergebnis Gruppe="11" Gruppenart="PARTEI" Name="DKP">
            <Stimmergebnis Stimmart="DIREKT" Anzahl="n/a" Prozent="0.000000" AnzahlVergleich="n/a" ProzentVergleich="0.000000" Differenz="n/a" ProzentDifferenz="0.000000"/>
            <Stimmergebnis Stimmart="LISTE" Anzahl="n/a" Prozent="0.000000" AnzahlVergleich="n/a" ProzentVergleich="0.000000" Differenz="n/a" ProzentDifferenz="0.000000"/>
        </Gruppenergebnis>
        <Gruppenergebnis Gruppe="38" Gruppenart="PARTEI" Name="DM">
            <Stimmergebnis Stimmart="LISTE" Anzahl="n/a" Prozent="0.000000" AnzahlVergleich="n/a" ProzentVergleich="0.000000" Differenz="n/a" ProzentDifferenz="0.000000"/>
        </Gruppenergebnis>
        <Gruppenergebnis Gruppe="43" Gruppenart="PARTEI" Name="Die Grauen">
            <Stimmergebnis Stimmart="DIREKT" Anzahl="n/a" Prozent="0.000000" AnzahlVergleich="n/a" ProzentVergleich="0.000000" Differenz="n/a" ProzentDifferenz="0.000000"/>
            <Stimmergebnis Stimmart="LISTE" Anzahl="n/a" Prozent="0.000000" AnzahlVergleich="n/a" ProzentVergleich="0.000000" Differenz="n/a" ProzentDifferenz="0.000000"/>
        </Gruppenergebnis>
        <Gruppenergebnis Gruppe="42" Gruppenart="PARTEI" Name="du.">
            <Stimmergebnis Stimmart="DIREKT" Anzahl="n/a" Prozent="0.000000" AnzahlVergleich="n/a" ProzentVergleich="0.000000" Differenz="n/a" ProzentDifferenz="0.000000"/>
            <Stimmergebnis Stimmart="LISTE" Anzahl="n/a" Prozent="0.000000" AnzahlVergleich="n/a" ProzentVergleich="0.000000" Differenz="n/a" ProzentDifferenz="0.000000"/>
        </Gruppenergebnis>
        <Gruppenergebnis Gruppe="19" Gruppenart="PARTEI" Name="MG">
            <Stimmergebnis Stimmart="DIREKT" Anzahl="n/a" Prozent="0.000000" AnzahlVergleich="n/a" ProzentVergleich="0.000000" Differenz="n/a" ProzentDifferenz="0.000000"/>
            <Stimmergebnis Stimmart="LISTE" Anzahl="n/a" Prozent="0.000000" AnzahlVergleich="n/a" ProzentVergleich="0.000000" Differenz="n/a" ProzentDifferenz="0.000000"/>
        </Gruppenergebnis>
        <Gruppenergebnis Gruppe="27" Gruppenart="PARTEI" Name="MENSCHLICHE WELT">
            <Stimmergebnis Stimmart="DIREKT" Anzahl="n/a" Prozent="0.000000" AnzahlVergleich="n/a" ProzentVergleich="0.000000" Differenz="n/a" ProzentDifferenz="0.000000"/>
            <Stimmergebnis Stimmart="LISTE" Anzahl="n/a" Prozent="0.000000" AnzahlVergleich="n/a" ProzentVergleich="0.000000" Differenz="n/a" ProzentDifferenz="0.000000"/>
        </Gruppenergebnis>
        <Gruppenergebnis Gruppe="44" Gruppenart="PARTEI" Name="Die Humanisten">
            <Stimmergebnis Stimmart="LISTE" Anzahl="n/a" Prozent="0.000000" AnzahlVergleich="n/a" ProzentVergleich="0.000000" Differenz="n/a" ProzentDifferenz="0.000000"/>
        </Gruppenergebnis>
        <Gruppenergebnis Gruppe="33" Gruppenart="PARTEI" Name="Gesundheitsforschung">
            <Stimmergebnis Stimmart="DIREKT" Anzahl="n/a" Prozent="0.000000" AnzahlVergleich="n/a" ProzentVergleich="0.000000" Differenz="n/a" ProzentDifferenz="0.000000"/>
            <Stimmergebnis Stimmart="LISTE" Anzahl="n/a" Prozent="0.000000" AnzahlVergleich="n/a" ProzentVergleich="0.000000" Differenz="n/a" ProzentDifferenz="0.000000"/>
        </Gruppenergebnis>
        <Gruppenergebnis Gruppe="20" Gruppenart="PARTEI" Name="V-Partei³">
            <Stimmergebnis Stimmart="DIREKT" Anzahl="n/a" Prozent="0.000000" AnzahlVergleich="n/a" ProzentVergleich="0.000000" Differenz="n/a" ProzentDifferenz="0.000000"/>
            <Stimmergebnis Stimmart="LISTE" Anzahl="n/a" Prozent="0.000000" AnzahlVergleich="n/a" ProzentVergleich="0.000000" Differenz="n/a" ProzentDifferenz="0.000000"/>
        </Gruppenergebnis>
        <Gruppenergebnis Gruppe="32" Gruppenart="PARTEI" Name="Bündnis C">
            <Stimmergebnis Stimmart="DIREKT" Anzahl="n/a" Prozent="0.000000" AnzahlVergleich="n/a" ProzentVergleich="0.000000" Differenz="n/a" ProzentDifferenz="0.000000"/>
        </Gruppenergebnis>
        <Gruppenergebnis Gruppe="48" Gruppenart="PARTEI" Name="DIE EINHEIT">
            <Stimmergebnis Stimmart="DIREKT" Anzahl="n/a" Prozent="0.000000" AnzahlVergleich="n/a" ProzentVergleich="0.000000" Differenz="n/a" ProzentDifferenz="0.000000"/>
        </Gruppenergebnis>
        <Gruppenergebnis Gruppe="30" Gruppenart="PARTEI" Name="DIE VIOLETTEN">
            <Stimmergebnis Stimmart="DIREKT" Anzahl="n/a" Prozent="0.000000" AnzahlVergleich="n/a" ProzentVergleich="0.000000" Differenz="n/a" ProzentDifferenz="0.000000"/>
        </Gruppenergebnis>
        <Gruppenergebnis Gruppe="31" Gruppenart="PARTEI" Name="FAMILIE">
            <Stimmergebnis Stimmart="DIREKT" Anzahl="n/a" Prozent="0.000000" AnzahlVergleich="1022" ProzentVergleich="0.010780" Differenz="n/a" ProzentDifferenz="-0.010780"/>
        </Gruppenergebnis>
        <Gruppenergebnis Gruppe="53" Gruppenart="PARTEI" Name="DIE FRAUEN">
            <Stimmergebnis Stimmart="DIREKT" Anzahl="n/a" Prozent="0.000000" AnzahlVergleich="n/a" ProzentVergleich="0.000000" Differenz="n/a" ProzentDifferenz="0.000000"/>
        </Gruppenergebnis>
        <Gruppenergebnis Gruppe="47" Gruppenart="PARTEI" Name="MIETERPARTEI">
            <Stimmergebnis Stimmart="DIREKT" Anzahl="n/a" Prozent="0.000000" AnzahlVergleich="n/a" ProzentVergleich="0.000000" Differenz="n/a" ProzentDifferenz="0.000000"/>
        </Gruppenergebnis>
        <Gruppenergebnis Gruppe="39" Gruppenart="PARTEI" Name="Neue Liberale">
            <Stimmergebnis Stimmart="DIREKT" Anzahl="n/a" Prozent="0.000000" AnzahlVergleich="n/a" ProzentVergleich="0.000000" Differenz="n/a" ProzentDifferenz="0.000000"/>
        </Gruppenergebnis>
        <Gruppenergebnis Gruppe="16" Gruppenart="PARTEI" Name="UNABHÄNGIGE">
            <Stimmergebnis Stimmart="DIREKT" Anzahl="n/a" Prozent="0.000000" AnzahlVergleich="n/a" ProzentVergleich="0.000000" Differenz="n/a" ProzentDifferenz="0.000000"/>
        </Gruppenergebnis>
        <Gruppenergebnis Gruppe="28" Gruppenart="UEBRIGE" Name="Übrige">
            <Stimmergebnis Stimmart="DIREKT" Anzahl="n/a" Prozent="0.000000" AnzahlVergleich="12462" ProzentVergleich="0.131452" Differenz="n/a" ProzentDifferenz="-0.131452"/>
            <Stimmergebnis Stimmart="LISTE" Anzahl="n/a" Prozent="0.000000" AnzahlVergleich="40305" ProzentVergleich="0.424346" Differenz="n/a" ProzentDifferenz="-0.424346"/>
        </Gruppenergebnis>
    </Gebietsergebnis>
    <Gebietsergebnis ZeitErstEintreffen="2017-08-25T11:12:35.000+02:00" ZeitLetzteKorrektur="2017-08-25T11:12:35.000+02:00" AuswertungseinheitenErwartet="64" AuswertungseinheitenEingetroffen="14" ErgebnisVollstaendig="false" NrAenderung="0" Gebietsnummer="5" Gebietsart="LAND" UegGebietsnummer="99" UegGebietsart="BUND" AuswertungseinheitenGesamt="64">
        <GebietText>Nordrhein-Westfalen</GebietText>
        <Gruppenergebnis Gruppe="100" Gruppenart="ALLGEMEIN" Name="Wahlberechtigte">
            <Stimmergebnis Stimmart="KEINE" Anzahl="3015913" Prozent="n/a" AnzahlVergleich="3015913" ProzentVergleich="n/a" Differenz="0" ProzentDifferenz="n/a"/>
        </Gruppenergebnis>
        <Gruppenergebnis Gruppe="200" Gruppenart="ALLGEMEIN" Name="Wähler">
            <Stimmergebnis Stimmart="KEINE" Anzahl="2231318" Prozent="73.984826" AnzahlVergleich="2231318" ProzentVergleich="16.835620" Differenz="0" ProzentDifferenz="57.149206"/>
        </Gruppenergebnis>
        <Gruppenergebnis Gruppe="300" Gruppenart="ALLGEMEIN" Name="Ungültige">
            <Stimmergebnis Stimmart="DIREKT" Anzahl="88951" Prozent="3.986477" AnzahlVergleich="34390" ProzentVergleich="1.541242" Differenz="54561" ProzentDifferenz="2.445236"/>
            <Stimmergebnis Stimmart="LISTE" Anzahl="45051" Prozent="2.019030" AnzahlVergleich="26971" ProzentVergleich="1.208747" Differenz="18080" ProzentDifferenz="0.810284"/>
        </Gruppenergebnis>
        <Gruppenergebnis Gruppe="400" Gruppenart="ALLGEMEIN" Name="Gültige">
            <Stimmergebnis Stimmart="DIREKT" Anzahl="2142367" Prozent="96.013522" AnzahlVergleich="2196928" ProzentVergleich="98.458758" Differenz="-54561" ProzentDifferenz="-2.445236"/>
            <Stimmergebnis Stimmart="LISTE" Anzahl="2186267" Prozent="97.980969" AnzahlVergleich="2204347" ProzentVergleich="98.791253" Differenz="-18080" ProzentDifferenz="-0.810284"/>
        </Gruppenergebnis>
        <Gruppenergebnis Gruppe="2" Gruppenart="PARTEI" Name="CDU">
            <Stimmergebnis Stimmart="DIREKT" Anzahl="1020156" Prozent="47.618171" AnzahlVergleich="1020156" ProzentVergleich="46.435568" Differenz="0" ProzentDifferenz="1.182604"/>
            <Stimmergebnis Stimmart="LISTE" Anzahl="901861" Prozent="41.251182" AnzahlVergleich="901861" ProzentVergleich="40.912842" Differenz="0" ProzentDifferenz="0.338341"/>
        </Gruppenergebnis>
        <Gruppenergebnis Gruppe="1" Gruppenart="PARTEI" Name="SPD">
            <Stimmergebnis Stimmart="DIREKT" Anzahl="718833" Prozent="33.553214" AnzahlVergleich="718833" ProzentVergleich="32.719916" Differenz="0" ProzentDifferenz="0.833299"/>
            <Stimmergebnis Stimmart="LISTE" Anzahl="616484" Prozent="28.198019" AnzahlVergleich="616484" ProzentVergleich="27.966740" Differenz="0" ProzentDifferenz="0.231280"/>
        </Gruppenergebnis>
        <Gruppenergebnis Gruppe="5" Gruppenart="PARTEI" Name="GRÜNE">
            <Stimmergebnis Stimmart="DIREKT" Anzahl="169933" Prozent="7.932020" AnzahlVergleich="169933" ProzentVergleich="7.735028" Differenz="0" ProzentDifferenz="0.196993"/>
            <Stimmergebnis Stimmart="LISTE" Anzahl="211449" Prozent="9.671691" AnzahlVergleich="211449" ProzentVergleich="9.592365" Differenz="0" ProzentDifferenz="0.079327"/>
        </Gruppenergebnis>
        <Gruppenergebnis Gruppe="34" Gruppenart="PARTEI" Name="DIE LINKE">
            <Stimmergebnis Stimmart="DIREKT" Anzahl="109795" Prozent="5.124938" AnzahlVergleich="109795" ProzentVergleich="4.997660" Differenz="0" ProzentDifferenz="0.127279"/>
            <Stimmergebnis Stimmart="LISTE" Anzahl="134929" Prozent="6.171661" AnzahlVergleich="134929" ProzentVergleich="6.121042" Differenz="0" ProzentDifferenz="0.050620"/>
        </Gruppenergebnis>
        <Gruppenergebnis Gruppe="4" Gruppenart="PARTEI" Name="FDP">
            <Stimmergebnis Stimmart="DIREKT" Anzahl="60816" Prozent="2.838729" AnzahlVergleich="60816" ProzentVergleich="2.768229" Differenz="0" ProzentDifferenz="0.070500"/>
            <Stimmergebnis Stimmart="LISTE" Anzahl="139089" Prozent="6.361940" AnzahlVergleich="139089" ProzentVergleich="6.309760" Differenz="0" ProzentDifferenz="0.052180"/>
        </Gruppenergebnis>
        <Gruppenergebnis Gruppe="35" Gruppenart="PARTEI" Name="AfD">
            <Stimmergebnis Stimmart="DIREKT" Anzahl="32336" Prozent="1.509358" AnzahlVergleich="37855" ProzentVergleich="1.723088" Differenz="-5519" ProzentDifferenz="-0.213729"/>
            <Stimmergebnis Stimmart="LISTE" Anzahl="87245" Prozent="3.990592" AnzahlVergleich="87245" ProzentVergleich="3.957861" Differenz="0" ProzentDifferenz="0.032731"/>
        </Gruppenergebnis>
        <Gruppenergebnis Gruppe="8" Gruppenart="PARTEI" Name="PIRATEN">
            <Stimmergebnis Stimmart="DIREKT" Anzahl="27843" Prozent="1.299637" AnzahlVergleich="53328" ProzentVergleich="2.427390" Differenz="-25485" ProzentDifferenz="-1.127753"/>
            <Stimmergebnis Stimmart="LISTE" Anzahl="51443" Prozent="2.353006" AnzahlVergleich="51443" ProzentVergleich="2.333707" Differenz="0" ProzentDifferenz="0.019299"/>
        </Gruppenergebnis>
        <Gruppenergebnis Gruppe="21" Gruppenart="PARTEI" Name="NPD">
            <Stimmergebnis Stimmart="LISTE" Anzahl="17359" Prozent="0.794001" AnzahlVergleich="17359" ProzentVergleich="0.787489" Differenz="0" ProzentDifferenz="0.006513"/>
        </Gruppenergebnis>
        <Gruppenergebnis Gruppe="37" Gruppenart="PARTEI" Name="Die PARTEI">
            <Stimmergebnis Stimmart="DIREKT" Anzahl="907" Prozent="0.042336" AnzahlVergleich="907" ProzentVergleich="0.041285" Differenz="0" ProzentDifferenz="0.001051"/>
            <Stimmergebnis Stimmart="LISTE" Anzahl="10902" Prozent="0.498658" AnzahlVergleich="10902" ProzentVergleich="0.494568" Differenz="0" ProzentDifferenz="0.004090"/>
        </Gruppenergebnis>
        <Gruppenergebnis Gruppe="45" Gruppenart="PARTEI" Name="FREIE WÄHLER">
            <Stimmergebnis Stimmart="DIREKT" Anzahl="n/a" Prozent="0.000000" AnzahlVergleich="4203" ProzentVergleich="0.191313" Differenz="n/a" ProzentDifferenz="-0.191313"/>
            <Stimmergebnis Stimmart="LISTE" Anzahl="6610" Prozent="0.302341" AnzahlVergleich="6610" ProzentVergleich="0.299862" Differenz="0" ProzentDifferenz="0.002480"/>
        </Gruppenergebnis>
        <Gruppenergebnis Gruppe="40" Gruppenart="PARTEI" Name="Volksabstimmung">
            <Stimmergebnis Stimmart="DIREKT" Anzahl="1748" Prozent="0.081591" AnzahlVergleich="1748" ProzentVergleich="0.079566" Differenz="0" ProzentDifferenz="0.002026"/>
            <Stimmergebnis Stimmart="LISTE" Anzahl="4712" Prozent="0.215527" AnzahlVergleich="4712" ProzentVergleich="0.213759" Differenz="0" ProzentDifferenz="0.001768"/>
        </Gruppenergebnis>
        <Gruppenergebnis Gruppe="22" Gruppenart="PARTEI" Name="ÖDP">
            <Stimmergebnis Stimmart="DIREKT" Anzahl="n/a" Prozent="0.000000" AnzahlVergleich="n/a" ProzentVergleich="0.000000" Differenz="n/a" ProzentDifferenz="0.000000"/>
            <Stimmergebnis Stimmart="LISTE" Anzahl="3284" Prozent="0.150210" AnzahlVergleich="3284" ProzentVergleich="0.148978" Differenz="0" ProzentDifferenz="0.001232"/>
        </Gruppenergebnis>
        <Gruppenergebnis Gruppe="17" Gruppenart="PARTEI" Name="MLPD">
            <Stimmergebnis Stimmart="DIREKT" Anzahl="n/a" Prozent="0.000000" AnzahlVergleich="n/a" ProzentVergleich="0.000000" Differenz="n/a" ProzentDifferenz="0.000000"/>
            <Stimmergebnis Stimmart="LISTE" Anzahl="461" Prozent="0.021086" AnzahlVergleich="461" ProzentVergleich="0.020913" Differenz="0" ProzentDifferenz="0.000173"/>
        </Gruppenergebnis>
        <Gruppenergebnis Gruppe="15" Gruppenart="PARTEI" Name="SGP">
            <Stimmergebnis Stimmart="LISTE" Anzahl="439" Prozent="0.020079" AnzahlVergleich="439" ProzentVergleich="0.019915" Differenz="0" ProzentDifferenz="0.000165"/>
        </Gruppenergebnis>
        <Gruppenergebnis Gruppe="41" Gruppenart="PARTEI" Name="AD-DEMOKRATEN">
            <Stimmergebnis Stimmart="LISTE" Anzahl="n/a" Prozent="0.000000" AnzahlVergleich="n/a" ProzentVergleich="0.000000" Differenz="n/a" ProzentDifferenz="0.000000"/>
        </Gruppenergebnis>
        <Gruppenergebnis Gruppe="29" Gruppenart="PARTEI" Name="BGE">
            <Stimmergebnis Stimmart="LISTE" Anzahl="n/a" Prozent="0.000000" AnzahlVergleich="n/a" ProzentVergleich="0.000000" Differenz="n/a" ProzentDifferenz="0.000000"/>
        </Gruppenergebnis>
        <Gruppenergebnis Gruppe="24" Gruppenart="PARTEI" Name="DiB">
            <Stimmergebnis Stimmart="LISTE" Anzahl="n/a" Prozent="0.000000" AnzahlVergleich="n/a" ProzentVergleich="0.000000" Differenz="n/a" ProzentDifferenz="0.000000"/>
        </Gruppenergebnis>
        <Gruppenergebnis Gruppe="11" Gruppenart="PARTEI" Name="DKP">
            <Stimmergebnis Stimmart="DIREKT" Anzahl="n/a" Prozent="0.000000" AnzahlVergleich="n/a" ProzentVergleich="0.000000" Differenz="n/a" ProzentDifferenz="0.000000"/>
            <Stimmergebnis Stimmart="LISTE" Anzahl="n/a" Prozent="0.000000" AnzahlVergleich="n/a" ProzentVergleich="0.000000" Differenz="n/a" ProzentDifferenz="0.000000"/>
        </Gruppenergebnis>
        <Gruppenergebnis Gruppe="38" Gruppenart="PARTEI" Name="DM">
            <Stimmergebnis Stimmart="LISTE" Anzahl="n/a" Prozent="0.000000" AnzahlVergleich="n/a" ProzentVergleich="0.000000" Differenz="n/a" ProzentDifferenz="0.000000"/>
        </Gruppenergebnis>
        <Gruppenergebnis Gruppe="44" Gruppenart="PARTEI" Name="Die Humanisten">
            <Stimmergebnis Stimmart="LISTE" Anzahl="n/a" Prozent="0.000000" AnzahlVergleich="n/a" ProzentVergleich="0.000000" Differenz="n/a" ProzentDifferenz="0.000000"/>
        </Gruppenergebnis>
        <Gruppenergebnis Gruppe="33" Gruppenart="PARTEI" Name="Gesundheitsforschung">
            <Stimmergebnis Stimmart="LISTE" Anzahl="n/a" Prozent="0.000000" AnzahlVergleich="n/a" ProzentVergleich="0.000000" Differenz="n/a" ProzentDifferenz="0.000000"/>
        </Gruppenergebnis>
        <Gruppenergebnis Gruppe="9" Gruppenart="PARTEI" Name="Tierschutzpartei">
            <Stimmergebnis Stimmart="LISTE" Anzahl="n/a" Prozent="0.000000" AnzahlVergleich="n/a" ProzentVergleich="0.000000" Differenz="n/a" ProzentDifferenz="0.000000"/>
        </Gruppenergebnis>
        <Gruppenergebnis Gruppe="20" Gruppenart="PARTEI" Name="V-Partei³">
            <Stimmergebnis Stimmart="LISTE" Anzahl="n/a" Prozent="0.000000" AnzahlVergleich="n/a" ProzentVergleich="0.000000" Differenz="n/a" ProzentDifferenz="0.000000"/>
        </Gruppenergebnis>
        <Gruppenergebnis Gruppe="30" Gruppenart="PARTEI" Name="DIE VIOLETTEN">
            <Stimmergebnis Stimmart="DIREKT" Anzahl="n/a" Prozent="0.000000" AnzahlVergleich="n/a" ProzentVergleich="0.000000" Differenz="n/a" ProzentDifferenz="0.000000"/>
        </Gruppenergebnis>
        <Gruppenergebnis Gruppe="28" Gruppenart="UEBRIGE" Name="Übrige">
            <Stimmergebnis Stimmart="DIREKT" Anzahl="n/a" Prozent="0.000000" AnzahlVergleich="19354" ProzentVergleich="0.880957" Differenz="n/a" ProzentDifferenz="-0.880957"/>
            <Stimmergebnis Stimmart="LISTE" Anzahl="n/a" Prozent="0.000000" AnzahlVergleich="18080" ProzentVergleich="0.820198" Differenz="n/a" ProzentDifferenz="-0.820198"/>
        </Gruppenergebnis>
    </Gebietsergebnis>
    <Gebietsergebnis ZeitErstEintreffen="2017-08-25T11:12:35.000+02:00" ZeitLetzteKorrektur="2017-08-25T11:12:35.000+02:00" AuswertungseinheitenErwartet="1" AuswertungseinheitenEingetroffen="1" ErgebnisVollstaendig="true" NrAenderung="0" Gebietsnummer="95" Gebietsart="WAHLKREIS" UegGebietsnummer="5" UegGebietsart="LAND" AuswertungseinheitenGesamt="1">
        <GebietText>Köln III</GebietText>
        <Direktergebnis>
            <Gewinner Name="Dr. Mützenich, Rolf" Gruppe="1" Wahlergebnisart="VORLAEUFIG"/>
            <Gewinner Name="" Gruppe="1" Wahlergebnisart="VORPERIODE"/>
            <Erstunterlegener Name="Manderla, Gisela" Gruppe="2" Wahlergebnisart="VORLAEUFIG"/>
        </Direktergebnis>
        <Gruppenergebnis Gruppe="100" Gruppenart="ALLGEMEIN" Name="Wahlberechtigte">
            <Stimmergebnis Stimmart="KEINE" Anzahl="201922" Prozent="n/a" AnzahlVergleich="201922" ProzentVergleich="n/a" Differenz="0" ProzentDifferenz="n/a"/>
        </Gruppenergebnis>
        <Gruppenergebnis Gruppe="200" Gruppenart="ALLGEMEIN" Name="Wähler">
            <Stimmergebnis Stimmart="KEINE" Anzahl="141714" Prozent="70.182545" AnzahlVergleich="141714" ProzentVergleich="70.182546" Differenz="0" ProzentDifferenz="0.000000"/>
        </Gruppenergebnis>
        <Gruppenergebnis Gruppe="300" Gruppenart="ALLGEMEIN" Name="Ungültige">
            <Stimmergebnis Stimmart="DIREKT" Anzahl="8607" Prozent="6.073500" AnzahlVergleich="1765" ProzentVergleich="1.245466" Differenz="6842" ProzentDifferenz="4.828034"/>
            <Stimmergebnis Stimmart="LISTE" Anzahl="2961" Prozent="2.089419" AnzahlVergleich="1368" ProzentVergleich="0.965325" Differenz="1593" ProzentDifferenz="1.124095"/>
        </Gruppenergebnis>
        <Gruppenergebnis Gruppe="400" Gruppenart="ALLGEMEIN" Name="Gültige">
            <Stimmergebnis Stimmart="DIREKT" Anzahl="133107" Prozent="93.926499" AnzahlVergleich="139949" ProzentVergleich="98.754534" Differenz="-6842" ProzentDifferenz="-4.828034"/>
            <Stimmergebnis Stimmart="LISTE" Anzahl="138753" Prozent="97.910580" AnzahlVergleich="140346" ProzentVergleich="99.034675" Differenz="-1593" ProzentDifferenz="-1.124095"/>
        </Gruppenergebnis>
        <Gruppenergebnis Gruppe="2" Gruppenart="PARTEI" Name="CDU" Direktkandidat="Manderla,Gisela">
            <Stimmergebnis Stimmart="DIREKT" Anzahl="45999" Prozent="34.557912" AnzahlVergleich="45999" ProzentVergleich="32.868402" Differenz="0" ProzentDifferenz="1.689510"/>
            <Stimmergebnis Stimmart="LISTE" Anzahl="42902" Prozent="30.919691" AnzahlVergleich="42902" ProzentVergleich="30.568737" Differenz="0" ProzentDifferenz="0.350955"/>
        </Gruppenergebnis>
        <Gruppenergebnis Gruppe="1" Gruppenart="PARTEI" Name="SPD" Direktkandidat="Dr. Mützenich,Rolf">
            <Stimmergebnis Stimmart="DIREKT" Anzahl="55021" Prozent="41.335917" AnzahlVergleich="55021" ProzentVergleich="39.315036" Differenz="0" ProzentDifferenz="2.020882"/>
            <Stimmergebnis Stimmart="LISTE" Anzahl="44240" Prozent="31.883995" AnzahlVergleich="44240" ProzentVergleich="31.522095" Differenz="0" ProzentDifferenz="0.361900"/>
        </Gruppenergebnis>
        <Gruppenergebnis Gruppe="5" Gruppenart="PARTEI" Name="GRÜNE" Direktkandidat="Dröge,Katharina">
            <Stimmergebnis Stimmart="DIREKT" Anzahl="18046" Prozent="13.557513" AnzahlVergleich="18046" ProzentVergleich="12.894697" Differenz="0" ProzentDifferenz="0.662817"/>
            <Stimmergebnis Stimmart="LISTE" Anzahl="20905" Prozent="15.066340" AnzahlVergleich="20905" ProzentVergleich="14.895330" Differenz="0" ProzentDifferenz="0.171011"/>
        </Gruppenergebnis>
        <Gruppenergebnis Gruppe="34" Gruppenart="PARTEI" Name="DIE LINKE" Direktkandidat="Tokyürek,Güldane">
            <Stimmergebnis Stimmart="DIREKT" Anzahl="10883" Prozent="8.176128" AnzahlVergleich="10883" ProzentVergleich="7.776404" Differenz="0" ProzentDifferenz="0.399725"/>
            <Stimmergebnis Stimmart="LISTE" Anzahl="12960" Prozent="9.340338" AnzahlVergleich="12960" ProzentVergleich="9.234321" Differenz="0" ProzentDifferenz="0.106018"/>
        </Gruppenergebnis>
        <Gruppenergebnis Gruppe="4" Gruppenart="PARTEI" Name="FDP" Direktkandidat="Görzel,Volker">
            <Stimmergebnis Stimmart="DIREKT" Anzahl="3158" Prozent="2.372527" AnzahlVergleich="3158" ProzentVergleich="2.256536" Differenz="0" ProzentDifferenz="0.115991"/>
            <Stimmergebnis Stimmart="LISTE" Anzahl="6339" Prozent="4.568549" AnzahlVergleich="6339" ProzentVergleich="4.516694" Differenz="0" ProzentDifferenz="0.051856"/>
        </Gruppenergebnis>
        <Gruppenergebnis Gruppe="35" Gruppenart="PARTEI" Name="AfD" Direktkandidat="Boyens,Stephan">
            <Stimmergebnis Stimmart="DIREKT" Anzahl="n/a" Prozent="0.000000" AnzahlVergleich="n/a" ProzentVergleich="0.000000" Differenz="n/a" ProzentDifferenz="0.000000"/>
            <Stimmergebnis Stimmart="LISTE" Anzahl="4513" Prozent="3.252542" AnzahlVergleich="4513" ProzentVergleich="3.215624" Differenz="0" ProzentDifferenz="0.036918"/>
        </Gruppenergebnis>
        <Gruppenergebnis Gruppe="8" Gruppenart="PARTEI" Name="PIRATEN">
            <Stimmergebnis Stimmart="LISTE" Anzahl="3789" Prozent="2.730751" AnzahlVergleich="3789" ProzentVergleich="2.699756" Differenz="0" ProzentDifferenz="0.030996"/>
        </Gruppenergebnis>
        <Gruppenergebnis Gruppe="21" Gruppenart="PARTEI" Name="NPD">
            <Stimmergebnis Stimmart="LISTE" Anzahl="1057" Prozent="0.761785" AnzahlVergleich="1057" ProzentVergleich="0.753139" Differenz="0" ProzentDifferenz="0.008646"/>
        </Gruppenergebnis>
        <Gruppenergebnis Gruppe="37" Gruppenart="PARTEI" Name="Die PARTEI" Direktkandidat="Herrmann,Lukas">
            <Stimmergebnis Stimmart="DIREKT" Anzahl="n/a" Prozent="0.000000" AnzahlVergleich="n/a" ProzentVergleich="0.000000" Differenz="n/a" ProzentDifferenz="0.000000"/>
            <Stimmergebnis Stimmart="LISTE" Anzahl="1041" Prozent="0.750254" AnzahlVergleich="1041" ProzentVergleich="0.741738" Differenz="0" ProzentDifferenz="0.008516"/>
        </Gruppenergebnis>
        <Gruppenergebnis Gruppe="45" Gruppenart="PARTEI" Name="FREIE WÄHLER">
            <Stimmergebnis Stimmart="LISTE" Anzahl="405" Prozent="0.291885" AnzahlVergleich="405" ProzentVergleich="0.288573" Differenz="0" ProzentDifferenz="0.003313"/>
        </Gruppenergebnis>
        <Gruppenergebnis Gruppe="40" Gruppenart="PARTEI" Name="Volksabstimmung">
            <Stimmergebnis Stimmart="LISTE" Anzahl="248" Prozent="0.178734" AnzahlVergleich="248" ProzentVergleich="0.176706" Differenz="0" ProzentDifferenz="0.002029"/>
        </Gruppenergebnis>
        <Gruppenergebnis Gruppe="22" Gruppenart="PARTEI" Name="ÖDP">
            <Stimmergebnis Stimmart="LISTE" Anzahl="263" Prozent="0.189545" AnzahlVergleich="263" ProzentVergleich="0.187394" Differenz="0" ProzentDifferenz="0.002151"/>
        </Gruppenergebnis>
        <Gruppenergebnis Gruppe="17" Gruppenart="PARTEI" Name="MLPD" Direktkandidat="Sauter,Matthias">
            <Stimmergebnis Stimmart="DIREKT" Anzahl="n/a" Prozent="0.000000" AnzahlVergleich="n/a" ProzentVergleich="0.000000" Differenz="n/a" ProzentDifferenz="0.000000"/>
            <Stimmergebnis Stimmart="LISTE" Anzahl="57" Prozent="0.041080" AnzahlVergleich="57" ProzentVergleich="0.040614" Differenz="0" ProzentDifferenz="0.000466"/>
        </Gruppenergebnis>
        <Gruppenergebnis Gruppe="15" Gruppenart="PARTEI" Name="SGP">
            <Stimmergebnis Stimmart="LISTE" Anzahl="34" Prozent="0.024503" AnzahlVergleich="34" ProzentVergleich="0.024226" Differenz="0" ProzentDifferenz="0.000278"/>
        </Gruppenergebnis>
        <Gruppenergebnis Gruppe="41" Gruppenart="PARTEI" Name="AD-DEMOKRATEN">
            <Stimmergebnis Stimmart="LISTE" Anzahl="n/a" Prozent="0.000000" AnzahlVergleich="n/a" ProzentVergleich="0.000000" Differenz="n/a" ProzentDifferenz="0.000000"/>
        </Gruppenergebnis>
        <Gruppenergebnis Gruppe="29" Gruppenart="PARTEI" Name="BGE">
            <Stimmergebnis Stimmart="LISTE" Anzahl="n/a" Prozent="0.000000" AnzahlVergleich="n/a" ProzentVergleich="0.000000" Differenz="n/a" ProzentDifferenz="0.000000"/>
        </Gruppenergebnis>
        <Gruppenergebnis Gruppe="24" Gruppenart="PARTEI" Name="DiB">
            <Stimmergebnis Stimmart="LISTE" Anzahl="n/a" Prozent="0.000000" AnzahlVergleich="n/a" ProzentVergleich="0.000000" Differenz="n/a" ProzentDifferenz="0.000000"/>
        </Gruppenergebnis>
        <Gruppenergebnis Gruppe="11" Gruppenart="PARTEI" Name="DKP">
            <Stimmergebnis Stimmart="LISTE" Anzahl="n/a" Prozent="0.000000" AnzahlVergleich="n/a" ProzentVergleich="0.000000" Differenz="n/a" ProzentDifferenz="0.000000"/>
        </Gruppenergebnis>
        <Gruppenergebnis Gruppe="38" Gruppenart="PARTEI" Name="DM">
            <Stimmergebnis Stimmart="LISTE" Anzahl="n/a" Prozent="0.000000" AnzahlVergleich="n/a" ProzentVergleich="0.000000" Differenz="n/a" ProzentDifferenz="0.000000"/>
        </Gruppenergebnis>
        <Gruppenergebnis Gruppe="44" Gruppenart="PARTEI" Name="Die Humanisten">
            <Stimmergebnis Stimmart="LISTE" Anzahl="n/a" Prozent="0.000000" AnzahlVergleich="n/a" ProzentVergleich="0.000000" Differenz="n/a" ProzentDifferenz="0.000000"/>
        </Gruppenergebnis>
        <Gruppenergebnis Gruppe="33" Gruppenart="PARTEI" Name="Gesundheitsforschung">
            <Stimmergebnis Stimmart="LISTE" Anzahl="n/a" Prozent="0.000000" AnzahlVergleich="n/a" ProzentVergleich="0.000000" Differenz="n/a" ProzentDifferenz="0.000000"/>
        </Gruppenergebnis>
        <Gruppenergebnis Gruppe="9" Gruppenart="PARTEI" Name="Tierschutzpartei">
            <Stimmergebnis Stimmart="LISTE" Anzahl="n/a" Prozent="0.000000" AnzahlVergleich="n/a" ProzentVergleich="0.000000" Differenz="n/a" ProzentDifferenz="0.000000"/>
        </Gruppenergebnis>
        <Gruppenergebnis Gruppe="20" Gruppenart="PARTEI" Name="V-Partei³">
            <Stimmergebnis Stimmart="LISTE" Anzahl="n/a" Prozent="0.000000" AnzahlVergleich="n/a" ProzentVergleich="0.000000" Differenz="n/a" ProzentDifferenz="0.000000"/>
        </Gruppenergebnis>
        <Gruppenergebnis Gruppe="28" Gruppenart="UEBRIGE" Name="Übrige">
            <Stimmergebnis Stimmart="DIREKT" Anzahl="n/a" Prozent="0.000000" AnzahlVergleich="6842" ProzentVergleich="4.888924" Differenz="n/a" ProzentDifferenz="-4.888924"/>
            <Stimmergebnis Stimmart="LISTE" Anzahl="n/a" Prozent="0.000000" AnzahlVergleich="1593" ProzentVergleich="1.135052" Differenz="n/a" ProzentDifferenz="-1.135052"/>
        </Gruppenergebnis>
    </Gebietsergebnis>
</Ergebniseingang>
