<?xml version="1.0" encoding="UTF-8" standalone="yes"?>
<Ergebniseingang>
    <WahlMetadaten>
        <File Ursprungsname="erg3_0022001.xml" Erstellungszeit="2017-08-25T11:14:07.854+02:00" ErstellungszeitMillis="1503652447854" Ursprungsserver="wahltest1l.wi.stba.de" FileVersion="1"/>
        <Wahl Wahlart="BUNDESTAGSWAHL_BUND" Wahltermin="2017-09-24+02:00" WahlId="BTW_BUND 17" GebietsartAuswertungseinheit="WAHLKREIS" GebietsartWahleinheit="WAHLKREIS" GebietsartFExport="WAHLKREIS" GebietsartBestaetigung="LAND"/>
        <Lauf Programm="WAS" Version="1.12.2" Startzeit="1970-01-05T02:31:08.437+01:00" Master="wahltest1l.wi.stba.de" Server="wahltest1l.wi.stba.de">
            <Daten Eingabe="VORLAEUFIG" Vergleich="VORPERIODE" Qualitaet="PRODUKTION" Status="ZWISCHENERGEBNIS" ZustSeqNr="0"/>
            <Stimmeingabe>
                <Eingabestand AuswertungseinheitenEingegangen="207" AuswertungseinheitenGesamt="299" LetzteAuswertungseinheit="220" Eingang="2017-08-25T11:13:56.000+02:00"/>
            </Stimmeingabe>
        </Lauf>
    </WahlMetadaten>
    <Gebietsergebnis ZeitErstEintreffen="2017-08-25T11:14:02.000+02:00" ZeitLetzteKorrektur="2017-08-25T11:14:02.000+02:00" AuswertungseinheitenErwartet="299" AuswertungseinheitenEingetroffen="207" ErgebnisVollstaendig="false" NrAenderung="0" Gebietsnummer="99" Gebietsart="BUND" AuswertungseinheitenGesamt="299">
        <GebietText>Bundesgebiet</GebietText>
        <Gruppenergebnis Gruppe="100" Gruppenart="ALLGEMEIN" Name="Wahlberechtigte">
            <Stimmergebnis Stimmart="KEINE" Anzahl="42523253" Prozent="n/a" AnzahlVergleich="42523253" ProzentVergleich="n/a" Differenz="0" ProzentDifferenz="n/a"/>
        </Gruppenergebnis>
        <Gruppenergebnis Gruppe="200" Gruppenart="ALLGEMEIN" Name="Wähler">
            <Stimmergebnis Stimmart="KEINE" Anzahl="30947876" Prozent="72.778712" AnzahlVergleich="30947876" ProzentVergleich="49.958716" Differenz="0" ProzentDifferenz="22.819996"/>
        </Gruppenergebnis>
        <Gruppenergebnis Gruppe="300" Gruppenart="ALLGEMEIN" Name="Ungültige">
            <Stimmergebnis Stimmart="DIREKT" Anzahl="1418834" Prozent="4.584592" AnzahlVergleich="468842" ProzentVergleich="1.514941" Differenz="949992" ProzentDifferenz="3.069651"/>
            <Stimmergebnis Stimmart="LISTE" Anzahl="696413" Prozent="2.250277" AnzahlVergleich="392407" ProzentVergleich="1.267961" Differenz="304006" ProzentDifferenz="0.982316"/>
        </Gruppenergebnis>
        <Gruppenergebnis Gruppe="400" Gruppenart="ALLGEMEIN" Name="Gültige">
            <Stimmergebnis Stimmart="DIREKT" Anzahl="29529042" Prozent="95.415407" AnzahlVergleich="30479034" ProzentVergleich="98.485059" Differenz="-949992" ProzentDifferenz="-3.069651"/>
            <Stimmergebnis Stimmart="LISTE" Anzahl="30251463" Prozent="97.749722" AnzahlVergleich="30555469" ProzentVergleich="98.732039" Differenz="-304006" ProzentDifferenz="-0.982316"/>
        </Gruppenergebnis>
        <Gruppenergebnis Gruppe="2" Gruppenart="PARTEI" Name="CDU">
            <Stimmergebnis Stimmart="DIREKT" Anzahl="12506746" Prozent="42.354052" AnzahlVergleich="12506746" ProzentVergleich="41.033932" Differenz="0" ProzentDifferenz="1.320121"/>
            <Stimmergebnis Stimmart="LISTE" Anzahl="11391552" Prozent="37.656201" AnzahlVergleich="11391552" ProzentVergleich="37.281549" Differenz="0" ProzentDifferenz="0.374653"/>
        </Gruppenergebnis>
        <Gruppenergebnis Gruppe="1" Gruppenart="PARTEI" Name="SPD">
            <Stimmergebnis Stimmart="DIREKT" Anzahl="9921395" Prozent="33.598770" AnzahlVergleich="9921395" ProzentVergleich="32.551540" Differenz="0" ProzentDifferenz="1.047230"/>
            <Stimmergebnis Stimmart="LISTE" Anzahl="8597990" Prozent="28.421732" AnzahlVergleich="8597990" ProzentVergleich="28.138956" Differenz="0" ProzentDifferenz="0.282777"/>
        </Gruppenergebnis>
        <Gruppenergebnis Gruppe="34" Gruppenart="PARTEI" Name="DIE LINKE">
            <Stimmergebnis Stimmart="DIREKT" Anzahl="1421906" Prozent="4.815279" AnzahlVergleich="1428568" ProzentVergleich="4.687051" Differenz="-6662" ProzentDifferenz="0.128229"/>
            <Stimmergebnis Stimmart="LISTE" Anzahl="1678366" Prozent="5.548049" AnzahlVergleich="1678366" ProzentVergleich="5.492850" Differenz="0" ProzentDifferenz="0.055199"/>
        </Gruppenergebnis>
        <Gruppenergebnis Gruppe="5" Gruppenart="PARTEI" Name="GRÜNE">
            <Stimmergebnis Stimmart="DIREKT" Anzahl="2372224" Prozent="8.033528" AnzahlVergleich="2377999" ProzentVergleich="7.802081" Differenz="-5775" ProzentDifferenz="0.231447"/>
            <Stimmergebnis Stimmart="LISTE" Anzahl="2821173" Prozent="9.325740" AnzahlVergleich="2821173" ProzentVergleich="9.232956" Differenz="0" ProzentDifferenz="0.092785"/>
        </Gruppenergebnis>
        <Gruppenergebnis Gruppe="3" Gruppenart="PARTEI" Name="CSU">
            <Stimmergebnis Stimmart="DIREKT" Anzahl="1497437" Prozent="5.071065" AnzahlVergleich="1497437" ProzentVergleich="4.913007" Differenz="0" ProzentDifferenz="0.158058"/>
            <Stimmergebnis Stimmart="LISTE" Anzahl="1368127" Prozent="4.522515" AnzahlVergleich="1368127" ProzentVergleich="4.477519" Differenz="0" ProzentDifferenz="0.044996"/>
        </Gruppenergebnis>
        <Gruppenergebnis Gruppe="4" Gruppenart="PARTEI" Name="FDP">
            <Stimmergebnis Stimmart="DIREKT" Anzahl="766478" Prozent="2.595675" AnzahlVergleich="766478" ProzentVergleich="2.514771" Differenz="0" ProzentDifferenz="0.080904"/>
            <Stimmergebnis Stimmart="LISTE" Anzahl="1635714" Prozent="5.407057" AnzahlVergleich="1635714" ProzentVergleich="5.353261" Differenz="0" ProzentDifferenz="0.053797"/>
        </Gruppenergebnis>
        <Gruppenergebnis Gruppe="35" Gruppenart="PARTEI" Name="AfD">
            <Stimmergebnis Stimmart="DIREKT" Anzahl="569144" Prozent="1.927404" AnzahlVergleich="589250" ProzentVergleich="1.933296" Differenz="-20106" ProzentDifferenz="-0.005892"/>
            <Stimmergebnis Stimmart="LISTE" Anzahl="1364760" Prozent="4.511385" AnzahlVergleich="1364760" ProzentVergleich="4.466500" Differenz="0" ProzentDifferenz="0.044885"/>
        </Gruppenergebnis>
        <Gruppenergebnis Gruppe="8" Gruppenart="PARTEI" Name="PIRATEN">
            <Stimmergebnis Stimmart="DIREKT" Anzahl="146901" Prozent="0.497479" AnzahlVergleich="642724" ProzentVergleich="2.108741" Differenz="-495823" ProzentDifferenz="-1.611261"/>
            <Stimmergebnis Stimmart="LISTE" Anzahl="589694" Prozent="1.949307" AnzahlVergleich="646416" ProzentVergleich="2.115549" Differenz="-56722" ProzentDifferenz="-0.166242"/>
        </Gruppenergebnis>
        <Gruppenergebnis Gruppe="21" Gruppenart="PARTEI" Name="NPD">
            <Stimmergebnis Stimmart="DIREKT" Anzahl="33537" Prozent="0.113572" AnzahlVergleich="300921" ProzentVergleich="0.987305" Differenz="-267384" ProzentDifferenz="-0.873732"/>
            <Stimmergebnis Stimmart="LISTE" Anzahl="283231" Prozent="0.936255" AnzahlVergleich="283231" ProzentVergleich="0.926940" Differenz="0" ProzentDifferenz="0.009316"/>
        </Gruppenergebnis>
        <Gruppenergebnis Gruppe="45" Gruppenart="PARTEI" Name="FREIE WÄHLER">
            <Stimmergebnis Stimmart="DIREKT" Anzahl="178917" Prozent="0.605901" AnzahlVergleich="241711" ProzentVergleich="0.793040" Differenz="-62794" ProzentDifferenz="-0.187138"/>
            <Stimmergebnis Stimmart="LISTE" Anzahl="218651" Prozent="0.722778" AnzahlVergleich="218651" ProzentVergleich="0.715587" Differenz="0" ProzentDifferenz="0.007191"/>
        </Gruppenergebnis>
        <Gruppenergebnis Gruppe="9" Gruppenart="PARTEI" Name="Tierschutzpartei">
            <Stimmergebnis Stimmart="DIREKT" Anzahl="n/a" Prozent="0.000000" AnzahlVergleich="n/a" ProzentVergleich="0.000000" Differenz="n/a" ProzentDifferenz="0.000000"/>
            <Stimmergebnis Stimmart="LISTE" Anzahl="96546" Prozent="0.319144" AnzahlVergleich="112889" ProzentVergleich="0.369456" Differenz="-16343" ProzentDifferenz="-0.050311"/>
        </Gruppenergebnis>
        <Gruppenergebnis Gruppe="22" Gruppenart="PARTEI" Name="ÖDP">
            <Stimmergebnis Stimmart="DIREKT" Anzahl="71529" Prozent="0.242232" AnzahlVergleich="88018" ProzentVergleich="0.288782" Differenz="-16489" ProzentDifferenz="-0.046549"/>
            <Stimmergebnis Stimmart="LISTE" Anzahl="78482" Prozent="0.259432" AnzahlVergleich="78482" ProzentVergleich="0.256851" Differenz="0" ProzentDifferenz="0.002581"/>
        </Gruppenergebnis>
        <Gruppenergebnis Gruppe="37" Gruppenart="PARTEI" Name="Die PARTEI">
            <Stimmergebnis Stimmart="DIREKT" Anzahl="15435" Prozent="0.052270" AnzahlVergleich="17705" ProzentVergleich="0.058089" Differenz="-2270" ProzentDifferenz="-0.005818"/>
            <Stimmergebnis Stimmart="LISTE" Anzahl="60001" Prozent="0.198340" AnzahlVergleich="60001" ProzentVergleich="0.196367" Differenz="0" ProzentDifferenz="0.001974"/>
        </Gruppenergebnis>
        <Gruppenergebnis Gruppe="18" Gruppenart="PARTEI" Name="BP">
            <Stimmergebnis Stimmart="DIREKT" Anzahl="15917" Prozent="0.053902" AnzahlVergleich="15917" ProzentVergleich="0.052223" Differenz="0" ProzentDifferenz="0.001680"/>
            <Stimmergebnis Stimmart="LISTE" Anzahl="32671" Prozent="0.107998" AnzahlVergleich="32671" ProzentVergleich="0.106924" Differenz="0" ProzentDifferenz="0.001074"/>
        </Gruppenergebnis>
        <Gruppenergebnis Gruppe="40" Gruppenart="PARTEI" Name="Volksabstimmung">
            <Stimmergebnis Stimmart="DIREKT" Anzahl="1748" Prozent="0.005919" AnzahlVergleich="1748" ProzentVergleich="0.005735" Differenz="0" ProzentDifferenz="0.000185"/>
            <Stimmergebnis Stimmart="LISTE" Anzahl="17622" Prozent="0.058251" AnzahlVergleich="28654" ProzentVergleich="0.093777" Differenz="-11032" ProzentDifferenz="-0.035525"/>
        </Gruppenergebnis>
        <Gruppenergebnis Gruppe="36" Gruppenart="PARTEI" Name="PDV">
            <Stimmergebnis Stimmart="DIREKT" Anzahl="n/a" Prozent="0.000000" AnzahlVergleich="2823" ProzentVergleich="0.009262" Differenz="n/a" ProzentDifferenz="-0.009262"/>
            <Stimmergebnis Stimmart="LISTE" Anzahl="n/a" Prozent="0.000000" AnzahlVergleich="20549" ProzentVergleich="0.067251" Differenz="n/a" ProzentDifferenz="-0.067251"/>
        </Gruppenergebnis>
        <Gruppenergebnis Gruppe="17" Gruppenart="PARTEI" Name="MLPD">
            <Stimmergebnis Stimmart="DIREKT" Anzahl="8069" Prozent="0.027325" AnzahlVergleich="8069" ProzentVergleich="0.026474" Differenz="0" ProzentDifferenz="0.000852"/>
            <Stimmergebnis Stimmart="LISTE" Anzahl="12443" Prozent="0.041131" AnzahlVergleich="12443" ProzentVergleich="0.040723" Differenz="0" ProzentDifferenz="0.000409"/>
        </Gruppenergebnis>
        <Gruppenergebnis Gruppe="12" Gruppenart="PARTEI" Name="BüSo">
            <Stimmergebnis Stimmart="DIREKT" Anzahl="1659" Prozent="0.005618" AnzahlVergleich="3935" ProzentVergleich="0.012911" Differenz="-2276" ProzentDifferenz="-0.007293"/>
            <Stimmergebnis Stimmart="LISTE" Anzahl="2285" Prozent="0.007553" AnzahlVergleich="5302" ProzentVergleich="0.017352" Differenz="-3017" ProzentDifferenz="-0.009799"/>
        </Gruppenergebnis>
        <Gruppenergebnis Gruppe="15" Gruppenart="PARTEI" Name="SGP">
            <Stimmergebnis Stimmart="DIREKT" Anzahl="n/a" Prozent="0.000000" AnzahlVergleich="n/a" ProzentVergleich="0.000000" Differenz="n/a" ProzentDifferenz="0.000000"/>
            <Stimmergebnis Stimmart="LISTE" Anzahl="2155" Prozent="0.007123" AnzahlVergleich="3599" ProzentVergleich="0.011779" Differenz="-1444" ProzentDifferenz="-0.004655"/>
        </Gruppenergebnis>
        <Gruppenergebnis Gruppe="14" Gruppenart="PARTEI" Name="DIE RECHTE">
            <Stimmergebnis Stimmart="DIREKT" Anzahl="n/a" Prozent="0.000000" AnzahlVergleich="n/a" ProzentVergleich="0.000000" Differenz="n/a" ProzentDifferenz="0.000000"/>
            <Stimmergebnis Stimmart="LISTE" Anzahl="n/a" Prozent="0.000000" AnzahlVergleich="2245" ProzentVergleich="0.007347" Differenz="n/a" ProzentDifferenz="-0.007347"/>
        </Gruppenergebnis>
        <Gruppenergebnis Gruppe="41" Gruppenart="PARTEI" Name="AD-DEMOKRATEN">
            <Stimmergebnis Stimmart="LISTE" Anzahl="n/a" Prozent="0.000000" AnzahlVergleich="n/a" ProzentVergleich="0.000000" Differenz="n/a" ProzentDifferenz="0.000000"/>
        </Gruppenergebnis>
        <Gruppenergebnis Gruppe="10" Gruppenart="PARTEI" Name="Tierschutzallianz">
            <Stimmergebnis Stimmart="DIREKT" Anzahl="n/a" Prozent="0.000000" AnzahlVergleich="n/a" ProzentVergleich="0.000000" Differenz="n/a" ProzentDifferenz="0.000000"/>
            <Stimmergebnis Stimmart="LISTE" Anzahl="n/a" Prozent="0.000000" AnzahlVergleich="n/a" ProzentVergleich="0.000000" Differenz="n/a" ProzentDifferenz="0.000000"/>
        </Gruppenergebnis>
        <Gruppenergebnis Gruppe="26" Gruppenart="PARTEI" Name="B*">
            <Stimmergebnis Stimmart="DIREKT" Anzahl="n/a" Prozent="0.000000" AnzahlVergleich="n/a" ProzentVergleich="0.000000" Differenz="n/a" ProzentDifferenz="0.000000"/>
            <Stimmergebnis Stimmart="LISTE" Anzahl="n/a" Prozent="0.000000" AnzahlVergleich="n/a" ProzentVergleich="0.000000" Differenz="n/a" ProzentDifferenz="0.000000"/>
        </Gruppenergebnis>
        <Gruppenergebnis Gruppe="29" Gruppenart="PARTEI" Name="BGE">
            <Stimmergebnis Stimmart="LISTE" Anzahl="n/a" Prozent="0.000000" AnzahlVergleich="n/a" ProzentVergleich="0.000000" Differenz="n/a" ProzentDifferenz="0.000000"/>
        </Gruppenergebnis>
        <Gruppenergebnis Gruppe="24" Gruppenart="PARTEI" Name="DiB">
            <Stimmergebnis Stimmart="LISTE" Anzahl="n/a" Prozent="0.000000" AnzahlVergleich="n/a" ProzentVergleich="0.000000" Differenz="n/a" ProzentDifferenz="0.000000"/>
        </Gruppenergebnis>
        <Gruppenergebnis Gruppe="11" Gruppenart="PARTEI" Name="DKP">
            <Stimmergebnis Stimmart="DIREKT" Anzahl="n/a" Prozent="0.000000" AnzahlVergleich="231" ProzentVergleich="0.000758" Differenz="n/a" ProzentDifferenz="-0.000758"/>
            <Stimmergebnis Stimmart="LISTE" Anzahl="n/a" Prozent="0.000000" AnzahlVergleich="n/a" ProzentVergleich="0.000000" Differenz="n/a" ProzentDifferenz="0.000000"/>
        </Gruppenergebnis>
        <Gruppenergebnis Gruppe="38" Gruppenart="PARTEI" Name="DM">
            <Stimmergebnis Stimmart="LISTE" Anzahl="n/a" Prozent="0.000000" AnzahlVergleich="n/a" ProzentVergleich="0.000000" Differenz="n/a" ProzentDifferenz="0.000000"/>
        </Gruppenergebnis>
        <Gruppenergebnis Gruppe="43" Gruppenart="PARTEI" Name="Die Grauen">
            <Stimmergebnis Stimmart="DIREKT" Anzahl="n/a" Prozent="0.000000" AnzahlVergleich="n/a" ProzentVergleich="0.000000" Differenz="n/a" ProzentDifferenz="0.000000"/>
            <Stimmergebnis Stimmart="LISTE" Anzahl="n/a" Prozent="0.000000" AnzahlVergleich="n/a" ProzentVergleich="0.000000" Differenz="n/a" ProzentDifferenz="0.000000"/>
        </Gruppenergebnis>
        <Gruppenergebnis Gruppe="42" Gruppenart="PARTEI" Name="du.">
            <Stimmergebnis Stimmart="DIREKT" Anzahl="n/a" Prozent="0.000000" AnzahlVergleich="n/a" ProzentVergleich="0.000000" Differenz="n/a" ProzentDifferenz="0.000000"/>
            <Stimmergebnis Stimmart="LISTE" Anzahl="n/a" Prozent="0.000000" AnzahlVergleich="n/a" ProzentVergleich="0.000000" Differenz="n/a" ProzentDifferenz="0.000000"/>
        </Gruppenergebnis>
        <Gruppenergebnis Gruppe="19" Gruppenart="PARTEI" Name="MG">
            <Stimmergebnis Stimmart="DIREKT" Anzahl="n/a" Prozent="0.000000" AnzahlVergleich="n/a" ProzentVergleich="0.000000" Differenz="n/a" ProzentDifferenz="0.000000"/>
            <Stimmergebnis Stimmart="LISTE" Anzahl="n/a" Prozent="0.000000" AnzahlVergleich="n/a" ProzentVergleich="0.000000" Differenz="n/a" ProzentDifferenz="0.000000"/>
        </Gruppenergebnis>
        <Gruppenergebnis Gruppe="27" Gruppenart="PARTEI" Name="MENSCHLICHE WELT">
            <Stimmergebnis Stimmart="DIREKT" Anzahl="n/a" Prozent="0.000000" AnzahlVergleich="n/a" ProzentVergleich="0.000000" Differenz="n/a" ProzentDifferenz="0.000000"/>
            <Stimmergebnis Stimmart="LISTE" Anzahl="n/a" Prozent="0.000000" AnzahlVergleich="n/a" ProzentVergleich="0.000000" Differenz="n/a" ProzentDifferenz="0.000000"/>
        </Gruppenergebnis>
        <Gruppenergebnis Gruppe="44" Gruppenart="PARTEI" Name="Die Humanisten">
            <Stimmergebnis Stimmart="LISTE" Anzahl="n/a" Prozent="0.000000" AnzahlVergleich="n/a" ProzentVergleich="0.000000" Differenz="n/a" ProzentDifferenz="0.000000"/>
        </Gruppenergebnis>
        <Gruppenergebnis Gruppe="33" Gruppenart="PARTEI" Name="Gesundheitsforschung">
            <Stimmergebnis Stimmart="DIREKT" Anzahl="n/a" Prozent="0.000000" AnzahlVergleich="n/a" ProzentVergleich="0.000000" Differenz="n/a" ProzentDifferenz="0.000000"/>
            <Stimmergebnis Stimmart="LISTE" Anzahl="n/a" Prozent="0.000000" AnzahlVergleich="n/a" ProzentVergleich="0.000000" Differenz="n/a" ProzentDifferenz="0.000000"/>
        </Gruppenergebnis>
        <Gruppenergebnis Gruppe="20" Gruppenart="PARTEI" Name="V-Partei³">
            <Stimmergebnis Stimmart="DIREKT" Anzahl="n/a" Prozent="0.000000" AnzahlVergleich="n/a" ProzentVergleich="0.000000" Differenz="n/a" ProzentDifferenz="0.000000"/>
            <Stimmergebnis Stimmart="LISTE" Anzahl="n/a" Prozent="0.000000" AnzahlVergleich="n/a" ProzentVergleich="0.000000" Differenz="n/a" ProzentDifferenz="0.000000"/>
        </Gruppenergebnis>
        <Gruppenergebnis Gruppe="32" Gruppenart="PARTEI" Name="Bündnis C">
            <Stimmergebnis Stimmart="DIREKT" Anzahl="n/a" Prozent="0.000000" AnzahlVergleich="n/a" ProzentVergleich="0.000000" Differenz="n/a" ProzentDifferenz="0.000000"/>
        </Gruppenergebnis>
        <Gruppenergebnis Gruppe="48" Gruppenart="PARTEI" Name="DIE EINHEIT">
            <Stimmergebnis Stimmart="DIREKT" Anzahl="n/a" Prozent="0.000000" AnzahlVergleich="n/a" ProzentVergleich="0.000000" Differenz="n/a" ProzentDifferenz="0.000000"/>
        </Gruppenergebnis>
        <Gruppenergebnis Gruppe="30" Gruppenart="PARTEI" Name="DIE VIOLETTEN">
            <Stimmergebnis Stimmart="DIREKT" Anzahl="n/a" Prozent="0.000000" AnzahlVergleich="1626" ProzentVergleich="0.005335" Differenz="n/a" ProzentDifferenz="-0.005335"/>
        </Gruppenergebnis>
        <Gruppenergebnis Gruppe="31" Gruppenart="PARTEI" Name="FAMILIE">
            <Stimmergebnis Stimmart="DIREKT" Anzahl="n/a" Prozent="0.000000" AnzahlVergleich="4478" ProzentVergleich="0.014692" Differenz="n/a" ProzentDifferenz="-0.014692"/>
        </Gruppenergebnis>
        <Gruppenergebnis Gruppe="53" Gruppenart="PARTEI" Name="DIE FRAUEN">
            <Stimmergebnis Stimmart="DIREKT" Anzahl="n/a" Prozent="0.000000" AnzahlVergleich="n/a" ProzentVergleich="0.000000" Differenz="n/a" ProzentDifferenz="0.000000"/>
        </Gruppenergebnis>
        <Gruppenergebnis Gruppe="47" Gruppenart="PARTEI" Name="MIETERPARTEI">
            <Stimmergebnis Stimmart="DIREKT" Anzahl="n/a" Prozent="0.000000" AnzahlVergleich="n/a" ProzentVergleich="0.000000" Differenz="n/a" ProzentDifferenz="0.000000"/>
        </Gruppenergebnis>
        <Gruppenergebnis Gruppe="39" Gruppenart="PARTEI" Name="Neue Liberale">
            <Stimmergebnis Stimmart="DIREKT" Anzahl="n/a" Prozent="0.000000" AnzahlVergleich="n/a" ProzentVergleich="0.000000" Differenz="n/a" ProzentDifferenz="0.000000"/>
        </Gruppenergebnis>
        <Gruppenergebnis Gruppe="16" Gruppenart="PARTEI" Name="UNABHÄNGIGE">
            <Stimmergebnis Stimmart="DIREKT" Anzahl="n/a" Prozent="0.000000" AnzahlVergleich="n/a" ProzentVergleich="0.000000" Differenz="n/a" ProzentDifferenz="0.000000"/>
        </Gruppenergebnis>
        <Gruppenergebnis Gruppe="28" Gruppenart="UEBRIGE" Name="Übrige">
            <Stimmergebnis Stimmart="DIREKT" Anzahl="n/a" Prozent="0.000000" AnzahlVergleich="61255" ProzentVergleich="0.200974" Differenz="n/a" ProzentDifferenz="-0.200974"/>
            <Stimmergebnis Stimmart="LISTE" Anzahl="n/a" Prozent="0.000000" AnzahlVergleich="192654" ProzentVergleich="0.630506" Differenz="n/a" ProzentDifferenz="-0.630506"/>
        </Gruppenergebnis>
    </Gebietsergebnis>
    <Gebietsergebnis ZeitErstEintreffen="2017-08-25T11:14:02.000+02:00" ZeitLetzteKorrektur="2017-08-25T11:14:02.000+02:00" AuswertungseinheitenErwartet="46" AuswertungseinheitenEingetroffen="19" ErgebnisVollstaendig="false" NrAenderung="0" Gebietsnummer="9" Gebietsart="LAND" UegGebietsnummer="99" UegGebietsart="BUND" AuswertungseinheitenGesamt="46">
        <GebietText>Bayern</GebietText>
        <Gruppenergebnis Gruppe="100" Gruppenart="ALLGEMEIN" Name="Wahlberechtigte">
            <Stimmergebnis Stimmart="KEINE" Anzahl="3939099" Prozent="n/a" AnzahlVergleich="3939099" ProzentVergleich="n/a" Differenz="0" ProzentDifferenz="n/a"/>
        </Gruppenergebnis>
        <Gruppenergebnis Gruppe="200" Gruppenart="ALLGEMEIN" Name="Wähler">
            <Stimmergebnis Stimmart="KEINE" Anzahl="2777432" Prozent="70.509322" AnzahlVergleich="2777432" ProzentVergleich="29.320266" Differenz="0" ProzentDifferenz="41.189056"/>
        </Gruppenergebnis>
        <Gruppenergebnis Gruppe="300" Gruppenart="ALLGEMEIN" Name="Ungültige">
            <Stimmergebnis Stimmart="DIREKT" Anzahl="119287" Prozent="4.294866" AnzahlVergleich="24255" ProzentVergleich="0.873289" Differenz="95032" ProzentDifferenz="3.421578"/>
            <Stimmergebnis Stimmart="LISTE" Anzahl="42110" Prozent="1.516148" AnzahlVergleich="18518" ProzentVergleich="0.666731" Differenz="23592" ProzentDifferenz="0.849418"/>
        </Gruppenergebnis>
        <Gruppenergebnis Gruppe="400" Gruppenart="ALLGEMEIN" Name="Gültige">
            <Stimmergebnis Stimmart="DIREKT" Anzahl="2658145" Prozent="95.705133" AnzahlVergleich="2753177" ProzentVergleich="99.126711" Differenz="-95032" ProzentDifferenz="-3.421578"/>
            <Stimmergebnis Stimmart="LISTE" Anzahl="2735322" Prozent="98.483851" AnzahlVergleich="2758914" ProzentVergleich="99.333269" Differenz="-23592" ProzentDifferenz="-0.849418"/>
        </Gruppenergebnis>
        <Gruppenergebnis Gruppe="3" Gruppenart="PARTEI" Name="CSU">
            <Stimmergebnis Stimmart="DIREKT" Anzahl="1497437" Prozent="56.333909" AnzahlVergleich="1497437" ProzentVergleich="54.389420" Differenz="0" ProzentDifferenz="1.944490"/>
            <Stimmergebnis Stimmart="LISTE" Anzahl="1368127" Prozent="50.017036" AnzahlVergleich="1368127" ProzentVergleich="49.589331" Differenz="0" ProzentDifferenz="0.427705"/>
        </Gruppenergebnis>
        <Gruppenergebnis Gruppe="1" Gruppenart="PARTEI" Name="SPD">
            <Stimmergebnis Stimmart="DIREKT" Anzahl="553183" Prozent="20.810866" AnzahlVergleich="553183" ProzentVergleich="20.092533" Differenz="0" ProzentDifferenz="0.718333"/>
            <Stimmergebnis Stimmart="LISTE" Anzahl="503632" Prozent="18.412165" AnzahlVergleich="503632" ProzentVergleich="18.254719" Differenz="0" ProzentDifferenz="0.157446"/>
        </Gruppenergebnis>
        <Gruppenergebnis Gruppe="5" Gruppenart="PARTEI" Name="GRÜNE">
            <Stimmergebnis Stimmart="DIREKT" Anzahl="243611" Prozent="9.164699" AnzahlVergleich="243611" ProzentVergleich="8.848360" Differenz="0" ProzentDifferenz="0.316339"/>
            <Stimmergebnis Stimmart="LISTE" Anzahl="256852" Prozent="9.390192" AnzahlVergleich="256852" ProzentVergleich="9.309895" Differenz="0" ProzentDifferenz="0.080297"/>
        </Gruppenergebnis>
        <Gruppenergebnis Gruppe="4" Gruppenart="PARTEI" Name="FDP">
            <Stimmergebnis Stimmart="DIREKT" Anzahl="84129" Prozent="3.164951" AnzahlVergleich="84129" ProzentVergleich="3.055706" Differenz="0" ProzentDifferenz="0.109245"/>
            <Stimmergebnis Stimmart="LISTE" Anzahl="160152" Prozent="5.854959" AnzahlVergleich="160152" ProzentVergleich="5.804893" Differenz="0" ProzentDifferenz="0.050067"/>
        </Gruppenergebnis>
        <Gruppenergebnis Gruppe="35" Gruppenart="PARTEI" Name="AfD">
            <Stimmergebnis Stimmart="DIREKT" Anzahl="58082" Prozent="2.185057" AnzahlVergleich="58082" ProzentVergleich="2.109636" Differenz="0" ProzentDifferenz="0.075422"/>
            <Stimmergebnis Stimmart="LISTE" Anzahl="124111" Prozent="4.537345" AnzahlVergleich="124111" ProzentVergleich="4.498545" Differenz="0" ProzentDifferenz="0.038800"/>
        </Gruppenergebnis>
        <Gruppenergebnis Gruppe="34" Gruppenart="PARTEI" Name="DIE LINKE">
            <Stimmergebnis Stimmart="DIREKT" Anzahl="83992" Prozent="3.159797" AnzahlVergleich="83992" ProzentVergleich="3.050730" Differenz="0" ProzentDifferenz="0.109068"/>
            <Stimmergebnis Stimmart="LISTE" Anzahl="94301" Prozent="3.447528" AnzahlVergleich="94301" ProzentVergleich="3.418048" Differenz="0" ProzentDifferenz="0.029480"/>
        </Gruppenergebnis>
        <Gruppenergebnis Gruppe="45" Gruppenart="PARTEI" Name="FREIE WÄHLER">
            <Stimmergebnis Stimmart="DIREKT" Anzahl="66701" Prozent="2.509306" AnzahlVergleich="91682" ProzentVergleich="3.330044" Differenz="-24981" ProzentDifferenz="-0.820738"/>
            <Stimmergebnis Stimmart="LISTE" Anzahl="72767" Prozent="2.660271" AnzahlVergleich="72767" ProzentVergleich="2.637523" Differenz="0" ProzentDifferenz="0.022749"/>
        </Gruppenergebnis>
        <Gruppenergebnis Gruppe="8" Gruppenart="PARTEI" Name="PIRATEN">
            <Stimmergebnis Stimmart="DIREKT" Anzahl="7232" Prozent="0.272069" AnzahlVergleich="54805" ProzentVergleich="1.990609" Differenz="-47573" ProzentDifferenz="-1.718540"/>
            <Stimmergebnis Stimmart="LISTE" Anzahl="52045" Prozent="1.902701" AnzahlVergleich="52045" ProzentVergleich="1.886431" Differenz="0" ProzentDifferenz="0.016270"/>
        </Gruppenergebnis>
        <Gruppenergebnis Gruppe="22" Gruppenart="PARTEI" Name="ÖDP">
            <Stimmergebnis Stimmart="DIREKT" Anzahl="45742" Prozent="1.720824" AnzahlVergleich="48252" ProzentVergleich="1.752593" Differenz="-2510" ProzentDifferenz="-0.031769"/>
            <Stimmergebnis Stimmart="LISTE" Anzahl="33249" Prozent="1.215542" AnzahlVergleich="33249" ProzentVergleich="1.205148" Differenz="0" ProzentDifferenz="0.010394"/>
        </Gruppenergebnis>
        <Gruppenergebnis Gruppe="18" Gruppenart="PARTEI" Name="BP">
            <Stimmergebnis Stimmart="DIREKT" Anzahl="15917" Prozent="0.598801" AnzahlVergleich="15917" ProzentVergleich="0.578132" Differenz="0" ProzentDifferenz="0.020669"/>
            <Stimmergebnis Stimmart="LISTE" Anzahl="32671" Prozent="1.194411" AnzahlVergleich="32671" ProzentVergleich="1.184198" Differenz="0" ProzentDifferenz="0.010213"/>
        </Gruppenergebnis>
        <Gruppenergebnis Gruppe="21" Gruppenart="PARTEI" Name="NPD">
            <Stimmergebnis Stimmart="DIREKT" Anzahl="n/a" Prozent="0.000000" AnzahlVergleich="12373" ProzentVergleich="0.449408" Differenz="n/a" ProzentDifferenz="-0.449408"/>
            <Stimmergebnis Stimmart="LISTE" Anzahl="16601" Prozent="0.606912" AnzahlVergleich="16601" ProzentVergleich="0.601722" Differenz="0" ProzentDifferenz="0.005190"/>
        </Gruppenergebnis>
        <Gruppenergebnis Gruppe="9" Gruppenart="PARTEI" Name="Tierschutzpartei">
            <Stimmergebnis Stimmart="LISTE" Anzahl="19460" Prozent="0.711433" AnzahlVergleich="19460" ProzentVergleich="0.705350" Differenz="0" ProzentDifferenz="0.006084"/>
        </Gruppenergebnis>
        <Gruppenergebnis Gruppe="17" Gruppenart="PARTEI" Name="MLPD">
            <Stimmergebnis Stimmart="DIREKT" Anzahl="164" Prozent="0.006169" AnzahlVergleich="164" ProzentVergleich="0.005957" Differenz="0" ProzentDifferenz="0.000213"/>
            <Stimmergebnis Stimmart="LISTE" Anzahl="605" Prozent="0.022118" AnzahlVergleich="605" ProzentVergleich="0.021929" Differenz="0" ProzentDifferenz="0.000189"/>
        </Gruppenergebnis>
        <Gruppenergebnis Gruppe="12" Gruppenart="PARTEI" Name="BüSo">
            <Stimmergebnis Stimmart="DIREKT" Anzahl="1377" Prozent="0.051803" AnzahlVergleich="1377" ProzentVergleich="0.050015" Differenz="0" ProzentDifferenz="0.001788"/>
            <Stimmergebnis Stimmart="LISTE" Anzahl="749" Prozent="0.027382" AnzahlVergleich="749" ProzentVergleich="0.027148" Differenz="0" ProzentDifferenz="0.000235"/>
        </Gruppenergebnis>
        <Gruppenergebnis Gruppe="29" Gruppenart="PARTEI" Name="BGE">
            <Stimmergebnis Stimmart="LISTE" Anzahl="n/a" Prozent="0.000000" AnzahlVergleich="n/a" ProzentVergleich="0.000000" Differenz="n/a" ProzentDifferenz="0.000000"/>
        </Gruppenergebnis>
        <Gruppenergebnis Gruppe="24" Gruppenart="PARTEI" Name="DiB">
            <Stimmergebnis Stimmart="LISTE" Anzahl="n/a" Prozent="0.000000" AnzahlVergleich="n/a" ProzentVergleich="0.000000" Differenz="n/a" ProzentDifferenz="0.000000"/>
        </Gruppenergebnis>
        <Gruppenergebnis Gruppe="11" Gruppenart="PARTEI" Name="DKP">
            <Stimmergebnis Stimmart="LISTE" Anzahl="n/a" Prozent="0.000000" AnzahlVergleich="n/a" ProzentVergleich="0.000000" Differenz="n/a" ProzentDifferenz="0.000000"/>
        </Gruppenergebnis>
        <Gruppenergebnis Gruppe="38" Gruppenart="PARTEI" Name="DM">
            <Stimmergebnis Stimmart="LISTE" Anzahl="n/a" Prozent="0.000000" AnzahlVergleich="n/a" ProzentVergleich="0.000000" Differenz="n/a" ProzentDifferenz="0.000000"/>
        </Gruppenergebnis>
        <Gruppenergebnis Gruppe="37" Gruppenart="PARTEI" Name="Die PARTEI">
            <Stimmergebnis Stimmart="DIREKT" Anzahl="578" Prozent="0.021744" AnzahlVergleich="1387" ProzentVergleich="0.050378" Differenz="-809" ProzentDifferenz="-0.028634"/>
            <Stimmergebnis Stimmart="LISTE" Anzahl="n/a" Prozent="0.000000" AnzahlVergleich="n/a" ProzentVergleich="0.000000" Differenz="n/a" ProzentDifferenz="0.000000"/>
        </Gruppenergebnis>
        <Gruppenergebnis Gruppe="33" Gruppenart="PARTEI" Name="Gesundheitsforschung">
            <Stimmergebnis Stimmart="LISTE" Anzahl="n/a" Prozent="0.000000" AnzahlVergleich="n/a" ProzentVergleich="0.000000" Differenz="n/a" ProzentDifferenz="0.000000"/>
        </Gruppenergebnis>
        <Gruppenergebnis Gruppe="20" Gruppenart="PARTEI" Name="V-Partei³">
            <Stimmergebnis Stimmart="LISTE" Anzahl="n/a" Prozent="0.000000" AnzahlVergleich="n/a" ProzentVergleich="0.000000" Differenz="n/a" ProzentDifferenz="0.000000"/>
        </Gruppenergebnis>
        <Gruppenergebnis Gruppe="32" Gruppenart="PARTEI" Name="Bündnis C">
            <Stimmergebnis Stimmart="DIREKT" Anzahl="n/a" Prozent="0.000000" AnzahlVergleich="n/a" ProzentVergleich="0.000000" Differenz="n/a" ProzentDifferenz="0.000000"/>
        </Gruppenergebnis>
        <Gruppenergebnis Gruppe="30" Gruppenart="PARTEI" Name="DIE VIOLETTEN">
            <Stimmergebnis Stimmart="DIREKT" Anzahl="n/a" Prozent="0.000000" AnzahlVergleich="654" ProzentVergleich="0.023754" Differenz="n/a" ProzentDifferenz="-0.023754"/>
        </Gruppenergebnis>
        <Gruppenergebnis Gruppe="16" Gruppenart="PARTEI" Name="UNABHÄNGIGE">
            <Stimmergebnis Stimmart="DIREKT" Anzahl="n/a" Prozent="0.000000" AnzahlVergleich="n/a" ProzentVergleich="0.000000" Differenz="n/a" ProzentDifferenz="0.000000"/>
        </Gruppenergebnis>
        <Gruppenergebnis Gruppe="28" Gruppenart="UEBRIGE" Name="Übrige">
            <Stimmergebnis Stimmart="DIREKT" Anzahl="n/a" Prozent="0.000000" AnzahlVergleich="6132" ProzentVergleich="0.222725" Differenz="n/a" ProzentDifferenz="-0.222725"/>
            <Stimmergebnis Stimmart="LISTE" Anzahl="n/a" Prozent="0.000000" AnzahlVergleich="23592" ProzentVergleich="0.855119" Differenz="n/a" ProzentDifferenz="-0.855119"/>
        </Gruppenergebnis>
    </Gebietsergebnis>
    <Gebietsergebnis ZeitErstEintreffen="2017-08-25T11:14:02.000+02:00" ZeitLetzteKorrektur="2017-08-25T11:14:02.000+02:00" AuswertungseinheitenErwartet="1" AuswertungseinheitenEingetroffen="1" ErgebnisVollstaendig="true" NrAenderung="0" Gebietsnummer="220" Gebietsart="WAHLKREIS" UegGebietsnummer="9" UegGebietsart="LAND" AuswertungseinheitenGesamt="1">
        <GebietText>München-West/Mitte</GebietText>
        <Direktergebnis>
            <Gewinner Name="Pilsinger, Stephan" Gruppe="3" Wahlergebnisart="VORLAEUFIG"/>
            <Gewinner Name="" Gruppe="3" Wahlergebnisart="VORPERIODE"/>
            <Erstunterlegener Name="Dr. Goodwin, Bernhard" Gruppe="1" Wahlergebnisart="VORLAEUFIG"/>
        </Direktergebnis>
        <Gruppenergebnis Gruppe="100" Gruppenart="ALLGEMEIN" Name="Wahlberechtigte">
            <Stimmergebnis Stimmart="KEINE" Anzahl="239700" Prozent="n/a" AnzahlVergleich="239700" ProzentVergleich="n/a" Differenz="0" ProzentDifferenz="n/a"/>
        </Gruppenergebnis>
        <Gruppenergebnis Gruppe="200" Gruppenart="ALLGEMEIN" Name="Wähler">
            <Stimmergebnis Stimmart="KEINE" Anzahl="174322" Prozent="72.725073" AnzahlVergleich="174322" ProzentVergleich="72.725073" Differenz="0" ProzentDifferenz="0.000000"/>
        </Gruppenergebnis>
        <Gruppenergebnis Gruppe="300" Gruppenart="ALLGEMEIN" Name="Ungültige">
            <Stimmergebnis Stimmart="DIREKT" Anzahl="7686" Prozent="4.409082" AnzahlVergleich="1303" ProzentVergleich="0.747467" Differenz="6383" ProzentDifferenz="3.661615"/>
            <Stimmergebnis Stimmart="LISTE" Anzahl="1995" Prozent="1.144433" AnzahlVergleich="789" ProzentVergleich="0.452611" Differenz="1206" ProzentDifferenz="0.691823"/>
        </Gruppenergebnis>
        <Gruppenergebnis Gruppe="400" Gruppenart="ALLGEMEIN" Name="Gültige">
            <Stimmergebnis Stimmart="DIREKT" Anzahl="166636" Prozent="95.590917" AnzahlVergleich="173019" ProzentVergleich="99.252533" Differenz="-6383" ProzentDifferenz="-3.661615"/>
            <Stimmergebnis Stimmart="LISTE" Anzahl="172327" Prozent="98.855566" AnzahlVergleich="173533" ProzentVergleich="99.547389" Differenz="-1206" ProzentDifferenz="-0.691823"/>
        </Gruppenergebnis>
        <Gruppenergebnis Gruppe="3" Gruppenart="PARTEI" Name="CSU" Direktkandidat="Pilsinger,Stephan">
            <Stimmergebnis Stimmart="DIREKT" Anzahl="73661" Prozent="44.204733" AnzahlVergleich="73661" ProzentVergleich="42.573937" Differenz="0" ProzentDifferenz="1.630797"/>
            <Stimmergebnis Stimmart="LISTE" Anzahl="64221" Prozent="37.266940" AnzahlVergleich="64221" ProzentVergleich="37.007947" Differenz="0" ProzentDifferenz="0.258993"/>
        </Gruppenergebnis>
        <Gruppenergebnis Gruppe="1" Gruppenart="PARTEI" Name="SPD" Direktkandidat="Dr. Goodwin,Bernhard">
            <Stimmergebnis Stimmart="DIREKT" Anzahl="49419" Prozent="29.656856" AnzahlVergleich="49419" ProzentVergleich="28.562759" Differenz="0" ProzentDifferenz="1.094098"/>
            <Stimmergebnis Stimmart="LISTE" Anzahl="41108" Prozent="23.854648" AnzahlVergleich="41108" ProzentVergleich="23.688866" Differenz="0" ProzentDifferenz="0.165782"/>
        </Gruppenergebnis>
        <Gruppenergebnis Gruppe="5" Gruppenart="PARTEI" Name="GRÜNE" Direktkandidat="Janecek,Dieter">
            <Stimmergebnis Stimmart="DIREKT" Anzahl="22743" Prozent="13.648311" AnzahlVergleich="22743" ProzentVergleich="13.144799" Differenz="0" ProzentDifferenz="0.503512"/>
            <Stimmergebnis Stimmart="LISTE" Anzahl="27068" Prozent="15.707347" AnzahlVergleich="27068" ProzentVergleich="15.598186" Differenz="0" ProzentDifferenz="0.109161"/>
        </Gruppenergebnis>
        <Gruppenergebnis Gruppe="4" Gruppenart="PARTEI" Name="FDP" Direktkandidat="Dr. Köhler,Lukas">
            <Stimmergebnis Stimmart="DIREKT" Anzahl="6984" Prozent="4.191171" AnzahlVergleich="6984" ProzentVergleich="4.036551" Differenz="0" ProzentDifferenz="0.154620"/>
            <Stimmergebnis Stimmart="LISTE" Anzahl="12850" Prozent="7.456753" AnzahlVergleich="12850" ProzentVergleich="7.404932" Differenz="0" ProzentDifferenz="0.051822"/>
        </Gruppenergebnis>
        <Gruppenergebnis Gruppe="35" Gruppenart="PARTEI" Name="AfD" Direktkandidat="Zimniok,Bernhard">
            <Stimmergebnis Stimmart="DIREKT" Anzahl="n/a" Prozent="0.000000" AnzahlVergleich="n/a" ProzentVergleich="0.000000" Differenz="n/a" ProzentDifferenz="0.000000"/>
            <Stimmergebnis Stimmart="LISTE" Anzahl="7249" Prozent="4.206537" AnzahlVergleich="7249" ProzentVergleich="4.177303" Differenz="0" ProzentDifferenz="0.029235"/>
        </Gruppenergebnis>
        <Gruppenergebnis Gruppe="34" Gruppenart="PARTEI" Name="DIE LINKE" Direktkandidat="Lehmann,Dominik">
            <Stimmergebnis Stimmart="DIREKT" Anzahl="7135" Prozent="4.281787" AnzahlVergleich="7135" ProzentVergleich="4.123825" Differenz="0" ProzentDifferenz="0.157963"/>
            <Stimmergebnis Stimmart="LISTE" Anzahl="8312" Prozent="4.823388" AnzahlVergleich="8312" ProzentVergleich="4.789867" Differenz="0" ProzentDifferenz="0.033521"/>
        </Gruppenergebnis>
        <Gruppenergebnis Gruppe="45" Gruppenart="PARTEI" Name="FREIE WÄHLER" Direktkandidat="Gebhard,Ludwig">
            <Stimmergebnis Stimmart="DIREKT" Anzahl="3713" Prozent="2.228209" AnzahlVergleich="3713" ProzentVergleich="2.146007" Differenz="0" ProzentDifferenz="0.082203"/>
            <Stimmergebnis Stimmart="LISTE" Anzahl="2387" Prozent="1.385157" AnzahlVergleich="2387" ProzentVergleich="1.375531" Differenz="0" ProzentDifferenz="0.009626"/>
        </Gruppenergebnis>
        <Gruppenergebnis Gruppe="8" Gruppenart="PARTEI" Name="PIRATEN">
            <Stimmergebnis Stimmart="LISTE" Anzahl="4313" Prozent="2.502799" AnzahlVergleich="4313" ProzentVergleich="2.485406" Differenz="0" ProzentDifferenz="0.017394"/>
        </Gruppenergebnis>
        <Gruppenergebnis Gruppe="22" Gruppenart="PARTEI" Name="ÖDP" Direktkandidat="Klauke,Andreas">
            <Stimmergebnis Stimmart="DIREKT" Anzahl="2796" Prozent="1.677908" AnzahlVergleich="2796" ProzentVergleich="1.616007" Differenz="0" ProzentDifferenz="0.061902"/>
            <Stimmergebnis Stimmart="LISTE" Anzahl="1770" Prozent="1.027117" AnzahlVergleich="1770" ProzentVergleich="1.019979" Differenz="0" ProzentDifferenz="0.007138"/>
        </Gruppenergebnis>
        <Gruppenergebnis Gruppe="18" Gruppenart="PARTEI" Name="BP" Direktkandidat="Seidl,Norbert">
            <Stimmergebnis Stimmart="DIREKT" Anzahl="n/a" Prozent="0.000000" AnzahlVergleich="n/a" ProzentVergleich="0.000000" Differenz="n/a" ProzentDifferenz="0.000000"/>
            <Stimmergebnis Stimmart="LISTE" Anzahl="1002" Prozent="0.581452" AnzahlVergleich="1002" ProzentVergleich="0.577412" Differenz="0" ProzentDifferenz="0.004041"/>
        </Gruppenergebnis>
        <Gruppenergebnis Gruppe="21" Gruppenart="PARTEI" Name="NPD">
            <Stimmergebnis Stimmart="LISTE" Anzahl="643" Prozent="0.373127" AnzahlVergleich="643" ProzentVergleich="0.370535" Differenz="0" ProzentDifferenz="0.002593"/>
        </Gruppenergebnis>
        <Gruppenergebnis Gruppe="9" Gruppenart="PARTEI" Name="Tierschutzpartei">
            <Stimmergebnis Stimmart="LISTE" Anzahl="1219" Prozent="0.707376" AnzahlVergleich="1219" ProzentVergleich="0.702460" Differenz="0" ProzentDifferenz="0.004916"/>
        </Gruppenergebnis>
        <Gruppenergebnis Gruppe="17" Gruppenart="PARTEI" Name="MLPD">
            <Stimmergebnis Stimmart="LISTE" Anzahl="125" Prozent="0.072536" AnzahlVergleich="125" ProzentVergleich="0.072032" Differenz="0" ProzentDifferenz="0.000505"/>
        </Gruppenergebnis>
        <Gruppenergebnis Gruppe="12" Gruppenart="PARTEI" Name="BüSo" Direktkandidat="Zuse,Werner">
            <Stimmergebnis Stimmart="DIREKT" Anzahl="185" Prozent="0.111020" AnzahlVergleich="185" ProzentVergleich="0.106925" Differenz="0" ProzentDifferenz="0.004095"/>
            <Stimmergebnis Stimmart="LISTE" Anzahl="60" Prozent="0.034817" AnzahlVergleich="60" ProzentVergleich="0.034576" Differenz="0" ProzentDifferenz="0.000242"/>
        </Gruppenergebnis>
        <Gruppenergebnis Gruppe="29" Gruppenart="PARTEI" Name="BGE">
            <Stimmergebnis Stimmart="LISTE" Anzahl="n/a" Prozent="0.000000" AnzahlVergleich="n/a" ProzentVergleich="0.000000" Differenz="n/a" ProzentDifferenz="0.000000"/>
        </Gruppenergebnis>
        <Gruppenergebnis Gruppe="24" Gruppenart="PARTEI" Name="DiB">
            <Stimmergebnis Stimmart="LISTE" Anzahl="n/a" Prozent="0.000000" AnzahlVergleich="n/a" ProzentVergleich="0.000000" Differenz="n/a" ProzentDifferenz="0.000000"/>
        </Gruppenergebnis>
        <Gruppenergebnis Gruppe="11" Gruppenart="PARTEI" Name="DKP">
            <Stimmergebnis Stimmart="LISTE" Anzahl="n/a" Prozent="0.000000" AnzahlVergleich="n/a" ProzentVergleich="0.000000" Differenz="n/a" ProzentDifferenz="0.000000"/>
        </Gruppenergebnis>
        <Gruppenergebnis Gruppe="38" Gruppenart="PARTEI" Name="DM">
            <Stimmergebnis Stimmart="LISTE" Anzahl="n/a" Prozent="0.000000" AnzahlVergleich="n/a" ProzentVergleich="0.000000" Differenz="n/a" ProzentDifferenz="0.000000"/>
        </Gruppenergebnis>
        <Gruppenergebnis Gruppe="37" Gruppenart="PARTEI" Name="Die PARTEI">
            <Stimmergebnis Stimmart="LISTE" Anzahl="n/a" Prozent="0.000000" AnzahlVergleich="n/a" ProzentVergleich="0.000000" Differenz="n/a" ProzentDifferenz="0.000000"/>
        </Gruppenergebnis>
        <Gruppenergebnis Gruppe="33" Gruppenart="PARTEI" Name="Gesundheitsforschung">
            <Stimmergebnis Stimmart="LISTE" Anzahl="n/a" Prozent="0.000000" AnzahlVergleich="n/a" ProzentVergleich="0.000000" Differenz="n/a" ProzentDifferenz="0.000000"/>
        </Gruppenergebnis>
        <Gruppenergebnis Gruppe="20" Gruppenart="PARTEI" Name="V-Partei³">
            <Stimmergebnis Stimmart="LISTE" Anzahl="n/a" Prozent="0.000000" AnzahlVergleich="n/a" ProzentVergleich="0.000000" Differenz="n/a" ProzentDifferenz="0.000000"/>
        </Gruppenergebnis>
        <Gruppenergebnis Gruppe="518" Gruppenart="EINZELKANDIDAT" Name="EB: Mertel" Direktkandidat="Dr. Mertel,Robert">
            <Stimmergebnis Stimmart="DIREKT" Anzahl="n/a" Prozent="0.000000" AnzahlVergleich="n/a" ProzentVergleich="0.000000" Differenz="n/a" ProzentDifferenz="0.000000"/>
        </Gruppenergebnis>
        <Gruppenergebnis Gruppe="28" Gruppenart="UEBRIGE" Name="Übrige">
            <Stimmergebnis Stimmart="DIREKT" Anzahl="n/a" Prozent="0.000000" AnzahlVergleich="6383" ProzentVergleich="3.689190" Differenz="n/a" ProzentDifferenz="-3.689190"/>
            <Stimmergebnis Stimmart="LISTE" Anzahl="n/a" Prozent="0.000000" AnzahlVergleich="1206" ProzentVergleich="0.694969" Differenz="n/a" ProzentDifferenz="-0.694969"/>
        </Gruppenergebnis>
    </Gebietsergebnis>
</Ergebniseingang>
